core/behavorial/mac_array/verilog/mac_8in.v
module mac_8in (out, a, b, clk, reset);

parameter bw = 8;
parameter bw_psum = 2*bw+6;
parameter pr = 8;

output reg signed [bw_psum-1:0] out;
input  [pr*bw-1:0] a;
input  [pr*bw-1:0] b;
input clk;
input reset;


reg signed		[2*bw-1:0]	product0	;
reg signed		[2*bw-1:0]	product1	;
reg signed		[2*bw-1:0]	product2	;
reg signed		[2*bw-1:0]	product3	;
reg signed		[2*bw-1:0]	product4	;
reg signed		[2*bw-1:0]	product5	;
reg signed		[2*bw-1:0]	product6	;
reg signed		[2*bw-1:0]	product7	;

always @ (posedge clk) begin
	if (reset) begin
		out <= 0;
		product0 <= 0;
		product1 <= 0;
		product2 <= 0;
		product3 <= 0;
		product4 <= 0;
		product5 <= 0;
		product6 <= 0;
		product7 <= 0;
	end
	else begin
		product0	<=	{{(bw){a[bw*	1	-1]}},	a[bw*	1	-1:bw*	0	]}	*	{{(bw){b[bw*	1	-1]}},	b[bw*	1	-1:	bw*	0	]};
		product1	<=	{{(bw){a[bw*	2	-1]}},	a[bw*	2	-1:bw*	1	]}	*	{{(bw){b[bw*	2	-1]}},	b[bw*	2	-1:	bw*	1	]};
		product2	<=	{{(bw){a[bw*	3	-1]}},	a[bw*	3	-1:bw*	2	]}	*	{{(bw){b[bw*	3	-1]}},	b[bw*	3	-1:	bw*	2	]};
		product3	<=	{{(bw){a[bw*	4	-1]}},	a[bw*	4	-1:bw*	3	]}	*	{{(bw){b[bw*	4	-1]}},	b[bw*	4	-1:	bw*	3	]};
		product4	<=	{{(bw){a[bw*	5	-1]}},	a[bw*	5	-1:bw*	4	]}	*	{{(bw){b[bw*	5	-1]}},	b[bw*	5	-1:	bw*	4	]};
		product5	<=	{{(bw){a[bw*	6	-1]}},	a[bw*	6	-1:bw*	5	]}	*	{{(bw){b[bw*	6	-1]}},	b[bw*	6	-1:	bw*	5	]};
		product6	<=	{{(bw){a[bw*	7	-1]}},	a[bw*	7	-1:bw*	6	]}	*	{{(bw){b[bw*	7	-1]}},	b[bw*	7	-1:	bw*	6	]};
		product7	<=	{{(bw){a[bw*	8	-1]}},	a[bw*	8	-1:bw*	7	]}	*	{{(bw){b[bw*	8	-1]}},	b[bw*	8	-1:	bw*	7	]};

		out <= product0 + product1 + product2 + product3 + product4 + product5 + product6 + product7;

	end
end








endmodule

core/behavorial/mac_array/verilog/mac_col.v
module mac_col (clk, reset, out, q_in, q_out, i_inst, fifo_wr, o_inst);

parameter bw = 8;
parameter bw_psum = 2*bw+6;
parameter pr = 8;
parameter col_id = 0;

output signed [bw_psum-1:0] out;
input  signed [pr*bw-1:0] q_in;
output signed [pr*bw-1:0] q_out;
input  clk, reset;
input  [1:0] i_inst; // [1]: execute, [0]: load 
output [1:0] o_inst; // [1]: execute, [0]: load 
output fifo_wr;
reg    load_ready_q;
reg    [3:0] cnt_q;
reg    [1:0] inst_q;
reg    [1:0] inst_2q;
reg    [1:0] inst_3q;
reg    [1:0] inst_4q;
reg   signed [pr*bw-1:0] query_q;
reg   signed [pr*bw-1:0] key_q;
wire [bw_psum-1:0] psum;

assign o_inst = inst_q;
assign fifo_wr = inst_4q[1];
assign q_out  = query_q;
assign out = psum;

mac_8in #(.bw(8), .bw_psum(bw_psum), .pr(8)) mac_8in_instance (
  .a(query_q), 
  .b(key_q),
  .out(psum),
  .clk(clk),
  .reset(reset)
); 


always @ (posedge clk) begin

  if (reset) begin

    cnt_q <= 0;
    load_ready_q <= 1;
    inst_q <= 0;
    inst_2q <= 0;
    inst_3q <= 0;
    inst_4q <= 0;

  end

  else begin

    inst_q <= i_inst;
    inst_2q <= inst_q;
    inst_3q <= inst_2q;
    inst_4q <= inst_3q;

    if (inst_q[0]) begin //load

       query_q <= q_in;

       if (cnt_q == col_id && load_ready_q) begin
         key_q <= q_in;
         load_ready_q <= 0;
       end

       else if (load_ready_q)
         cnt_q <= cnt_q + 1;
    end

    else if(inst_q[1]) begin
      query_q <= q_in;
    end

  end
end

endmodule

core/behavorial/mac_array/verilog/mac_col_tb.v
`timescale 1ns/1ps

module mac_col_tb;

reg clk = 0;
reg reset = 1;
reg [63:0] q_in = 0;
reg [1:0] i_inst = 0;

wire [21:0] out_0;
wire [63:0] q_out_0;
wire [1:0] o_inst_0;
wire fifo_wr_0;

wire [21:0] out_1;
wire [63:0] q_out_1;
wire [1:0] o_inst_1;
wire fifo_wr_1;

wire [21:0] out_2;
wire [63:0] q_out_2;
wire [1:0] o_inst_2;
wire fifo_wr_2;

parameter total_K = 3;
parameter total_Q = 3;

integer qk_file;
integer qk_scan_file;
integer  K[total_K-1:0][7:0];
integer  Q[total_Q-1:0][7:0];
integer  pred_result[total_K-1:0][total_Q-1:0];
//integer  result[total_cycle-1:0];
//integer  sum[total_cycle-1:0];

integer  captured_data;
`define NULL 0

integer i,j,k,t,p,q,s,u,m;


mac_col #(.bw(8), .bw_psum(22), .pr(8), .col_id(0)) mac_col_instance_0 (
      .clk(clk),
      .reset(reset),
      .out(out_0),
      .q_in(q_in),
      .q_out(q_out_0),
      .i_inst(i_inst),
      .o_inst(o_inst_0),
      .fifo_wr(fifo_wr_0)
);

mac_col #(.bw(8), .bw_psum(22), .pr(8), .col_id(1)) mac_col_instance_1 (
      .clk(clk),
      .reset(reset),
      .out(out_1),
      .q_in(q_out_0),
      .q_out(q_out_1),
      .i_inst(o_inst_0),
      .o_inst(o_inst_1),
      .fifo_wr(fifo_wr_1)
);

mac_col #(.bw(8), .bw_psum(22), .pr(8), .col_id(2)) mac_col_instance_2 (
      .clk(clk),
      .reset(reset),
      .out(out_2),
      .q_in(q_out_1),
      .q_out(q_out_2),
      .i_inst(o_inst_1),
      .o_inst(o_inst_2),
      .fifo_wr(fifo_wr_2)
);


initial begin 
      $dumpfile("mac_col_tb.vcd");
      $dumpvars(0, mac_col_tb);


      ///// Q data txt reading /////

      $display("##### Q data txt reading #####");


      qk_file = $fopen("qdata.txt", "r");

      for (q=0; q<total_Q; q=q+1) begin
            $display("Q vector: %d\n", q);
            for (j=0; j<8; j=j+1) begin
                  qk_scan_file = $fscanf(qk_file, "%d\n", captured_data);
                  Q[q][j] = captured_data;
                  $display("Data: %d\n", captured_data);
            end
      end
      /////////////////////////////////


      ///// K data txt reading /////

      $display("##### K data txt reading #####");


      qk_file = $fopen("kdata.txt", "r");

      for (q=0; q<total_K; q=q+1) begin
            $display("K vector: %d\n", q);
            for (j=0; j<8; j=j+1) begin
                  qk_scan_file = $fscanf(qk_file, "%d\n", captured_data);
                  K[q][j] = captured_data;
                  $display("Data: %d\n", captured_data);
            end
      end
      /////////////////////////////////


      ///// Predicted results calculation /////

      $display("##### K data txt reading #####");


      for (k=0; k<total_K; k=k+1) begin
            $display("K#: %d", k);
            for (q=0; q<total_Q; q=q+1) begin
                  $display("Q#: %d", q);
                  pred_result[k][q] = 0;
                  for (i=0; i<8; i=i+1) begin
                        pred_result[k][q] = pred_result[k][q] + Q[q][i]*K[k][i];
                  end
                  $display("Predicted psum: %d", pred_result[k][q]);
            end
      end
      /////////////////////////////////


      #1 clk = 1;
      #1 clk = 0; reset = 0;
      #1 clk = 1;
      #1 clk = 0; i_inst = 2'b01;
      #1 clk = 1;
      for (q=0; q<total_K; q=q+1) begin
            #1 clk = 0; q_in = {K[q][7][7:0], K[q][6][7:0], K[q][5][7:0], K[q][4][7:0], K[q][3][7:0], K[q][2][7:0], K[q][1][7:0], K[q][0][7:0]};
            if (q + 1 == total_K)
                  i_inst = 2'b00;
            #1 clk = 1;
      end

      for (i = 0; i < 10; i = i + 1) begin
            #1 clk = 0;
            #1 clk = 1;
      end

      #1 clk = 0; i_inst = 2'b10;
      #1 clk = 1;

      for (q=0; q<total_Q; q=q+1) begin
            #1 clk = 0; q_in = {Q[q][7][7:0], Q[q][6][7:0], Q[q][5][7:0], Q[q][4][7:0], Q[q][3][7:0], Q[q][2][7:0], Q[q][1][7:0], Q[q][0][7:0]};
            if (q + 1 == total_Q)
                  i_inst = 2'b00;
            #1 clk = 1;
      end

      for (i = 0; i < 10; i = i + 1) begin
            #1 clk = 0;
            #1 clk = 1;
      end

      #1 $display("Finished.");
      #1 $finish;
end

endmodule

core/behavorial/mac_array/mac_col_tb.vcd
$date
	Wed Mar  5 22:40:12 2025
$end
$version
	Icarus Verilog
$end
$timescale
	1ps
$end
$scope module mac_col_tb $end
$var wire 64 ! q_out_2 [63:0] $end
$var wire 64 " q_out_1 [63:0] $end
$var wire 64 # q_out_0 [63:0] $end
$var wire 22 $ out_2 [21:0] $end
$var wire 22 % out_1 [21:0] $end
$var wire 22 & out_0 [21:0] $end
$var wire 2 ' o_inst_2 [1:0] $end
$var wire 2 ( o_inst_1 [1:0] $end
$var wire 2 ) o_inst_0 [1:0] $end
$var wire 1 * fifo_wr_2 $end
$var wire 1 + fifo_wr_1 $end
$var wire 1 , fifo_wr_0 $end
$var reg 1 - clk $end
$var reg 2 . i_inst [1:0] $end
$var reg 64 / q_in [63:0] $end
$var reg 1 0 reset $end
$var integer 32 1 captured_data [31:0] $end
$var integer 32 2 i [31:0] $end
$var integer 32 3 j [31:0] $end
$var integer 32 4 k [31:0] $end
$var integer 32 5 q [31:0] $end
$var integer 32 6 qk_file [31:0] $end
$var integer 32 7 qk_scan_file [31:0] $end
$scope module mac_col_instance_0 $end
$var wire 1 - clk $end
$var wire 2 8 i_inst [1:0] $end
$var wire 2 9 o_inst [1:0] $end
$var wire 22 : out [21:0] $end
$var wire 64 ; q_in [63:0] $end
$var wire 64 < q_out [63:0] $end
$var wire 1 0 reset $end
$var wire 22 = psum [21:0] $end
$var wire 1 , fifo_wr $end
$var reg 4 > cnt_q [3:0] $end
$var reg 2 ? inst_2q [1:0] $end
$var reg 2 @ inst_3q [1:0] $end
$var reg 2 A inst_4q [1:0] $end
$var reg 2 B inst_q [1:0] $end
$var reg 64 C key_q [63:0] $end
$var reg 1 D load_ready_q $end
$var reg 64 E query_q [63:0] $end
$scope module mac_8in_instance $end
$var wire 64 F a [63:0] $end
$var wire 64 G b [63:0] $end
$var wire 1 - clk $end
$var wire 1 0 reset $end
$var reg 22 H out [21:0] $end
$var reg 16 I product0 [15:0] $end
$var reg 16 J product1 [15:0] $end
$var reg 16 K product2 [15:0] $end
$var reg 16 L product3 [15:0] $end
$var reg 16 M product4 [15:0] $end
$var reg 16 N product5 [15:0] $end
$var reg 16 O product6 [15:0] $end
$var reg 16 P product7 [15:0] $end
$upscope $end
$upscope $end
$scope module mac_col_instance_1 $end
$var wire 1 - clk $end
$var wire 2 Q i_inst [1:0] $end
$var wire 2 R o_inst [1:0] $end
$var wire 22 S out [21:0] $end
$var wire 64 T q_in [63:0] $end
$var wire 64 U q_out [63:0] $end
$var wire 1 0 reset $end
$var wire 22 V psum [21:0] $end
$var wire 1 + fifo_wr $end
$var reg 4 W cnt_q [3:0] $end
$var reg 2 X inst_2q [1:0] $end
$var reg 2 Y inst_3q [1:0] $end
$var reg 2 Z inst_4q [1:0] $end
$var reg 2 [ inst_q [1:0] $end
$var reg 64 \ key_q [63:0] $end
$var reg 1 ] load_ready_q $end
$var reg 64 ^ query_q [63:0] $end
$scope module mac_8in_instance $end
$var wire 64 _ a [63:0] $end
$var wire 64 ` b [63:0] $end
$var wire 1 - clk $end
$var wire 1 0 reset $end
$var reg 22 a out [21:0] $end
$var reg 16 b product0 [15:0] $end
$var reg 16 c product1 [15:0] $end
$var reg 16 d product2 [15:0] $end
$var reg 16 e product3 [15:0] $end
$var reg 16 f product4 [15:0] $end
$var reg 16 g product5 [15:0] $end
$var reg 16 h product6 [15:0] $end
$var reg 16 i product7 [15:0] $end
$upscope $end
$upscope $end
$scope module mac_col_instance_2 $end
$var wire 1 - clk $end
$var wire 2 j i_inst [1:0] $end
$var wire 2 k o_inst [1:0] $end
$var wire 22 l out [21:0] $end
$var wire 64 m q_in [63:0] $end
$var wire 64 n q_out [63:0] $end
$var wire 1 0 reset $end
$var wire 22 o psum [21:0] $end
$var wire 1 * fifo_wr $end
$var reg 4 p cnt_q [3:0] $end
$var reg 2 q inst_2q [1:0] $end
$var reg 2 r inst_3q [1:0] $end
$var reg 2 s inst_4q [1:0] $end
$var reg 2 t inst_q [1:0] $end
$var reg 64 u key_q [63:0] $end
$var reg 1 v load_ready_q $end
$var reg 64 w query_q [63:0] $end
$scope module mac_8in_instance $end
$var wire 64 x a [63:0] $end
$var wire 64 y b [63:0] $end
$var wire 1 - clk $end
$var wire 1 0 reset $end
$var reg 22 z out [21:0] $end
$var reg 16 { product0 [15:0] $end
$var reg 16 | product1 [15:0] $end
$var reg 16 } product2 [15:0] $end
$var reg 16 ~ product3 [15:0] $end
$var reg 16 !" product4 [15:0] $end
$var reg 16 "" product5 [15:0] $end
$var reg 16 #" product6 [15:0] $end
$var reg 16 $" product7 [15:0] $end
$upscope $end
$upscope $end
$upscope $end
$enddefinitions $end
#0
$dumpvars
bx $"
bx #"
bx ""
bx !"
bx ~
bx }
bx |
bx {
bx z
bx y
bx x
bx w
xv
bx u
bx t
bx s
bx r
bx q
bx p
bx o
bx n
bx m
bx l
bx k
bx j
bx i
bx h
bx g
bx f
bx e
bx d
bx c
bx b
bx a
bx `
bx _
bx ^
x]
bx \
bx [
bx Z
bx Y
bx X
bx W
bx V
bx U
bx T
bx S
bx R
bx Q
bx P
bx O
bx N
bx M
bx L
bx K
bx J
bx I
bx H
bx G
bx F
bx E
xD
bx C
bx B
bx A
bx @
bx ?
bx >
bx =
bx <
b0 ;
bx :
bx 9
b0 8
b1 7
b10000000000000000000000000000100 6
b11 5
b11 4
b1000 3
b1000 2
b110 1
10
b0 /
b0 .
0-
x,
x+
x*
bx )
bx (
bx '
bx &
bx %
bx $
bx #
bx "
bx !
$end
#1000
0,
0+
0*
b0 P
b0 O
b0 N
b0 M
b0 L
b0 K
b0 J
b0 I
b0 &
b0 :
b0 =
b0 H
b0 A
b0 @
b0 ?
b0 )
b0 9
b0 Q
b0 B
1D
b0 >
b0 i
b0 h
b0 g
b0 f
b0 e
b0 d
b0 c
b0 b
b0 %
b0 S
b0 V
b0 a
b0 Z
b0 Y
b0 X
b0 (
b0 R
b0 j
b0 [
1]
b0 W
b0 $"
b0 #"
b0 ""
b0 !"
b0 ~
b0 }
b0 |
b0 {
b0 $
b0 l
b0 o
b0 z
b0 s
b0 r
b0 q
b0 '
b0 k
b0 t
1v
b0 p
1-
#2000
00
0-
#3000
bx $"
bx #"
bx ""
bx !"
bx ~
bx }
bx |
bx {
bx i
bx h
bx g
bx f
bx e
bx d
bx c
bx b
bx P
bx O
bx N
bx M
bx L
bx K
bx J
bx I
1-
#4000
b1 .
b1 8
0-
#5000
bx &
bx :
bx =
bx H
b1 )
b1 9
b1 Q
b1 B
bx %
bx S
bx V
bx a
bx $
bx l
bx o
bx z
b0 5
1-
#6000
b11100000000000000011111101111111111111111100000001111111010 /
b11100000000000000011111101111111111111111100000001111111010 ;
0-
#7000
b1 (
b1 R
b1 j
b1 [
0D
b11100000000000000011111101111111111111111100000001111111010 C
b11100000000000000011111101111111111111111100000001111111010 G
b11100000000000000011111101111111111111111100000001111111010 #
b11100000000000000011111101111111111111111100000001111111010 <
b11100000000000000011111101111111111111111100000001111111010 T
b11100000000000000011111101111111111111111100000001111111010 E
b11100000000000000011111101111111111111111100000001111111010 F
b1 ?
b1 5
1-
#8000
b1111100111111011000000000000011000000000111110001111101100000000 /
b1111100111111011000000000000011000000000111110001111101100000000 ;
0-
#9000
b110001 P
b0 O
b1 N
b11001 M
b1 L
b100 K
b1001 J
b100100 I
b1111100111111011000000000000011000000000111110001111101100000000 #
b1111100111111011000000000000011000000000111110001111101100000000 <
b1111100111111011000000000000011000000000111110001111101100000000 T
b1111100111111011000000000000011000000000111110001111101100000000 E
b1111100111111011000000000000011000000000111110001111101100000000 F
b1 @
b1 W
b11100000000000000011111101111111111111111100000001111111010 "
b11100000000000000011111101111111111111111100000001111111010 U
b11100000000000000011111101111111111111111100000001111111010 m
b11100000000000000011111101111111111111111100000001111111010 ^
b11100000000000000011111101111111111111111100000001111111010 _
b1 X
b1 '
b1 k
b1 t
b10 5
1-
#10000
b0 .
b0 8
b11000000110000001110000011100000011111110101111100100000100 /
b11000000110000001110000011100000011111110101111100100000100 ;
0-
#11000
b1 p
b11100000000000000011111101111111111111111100000001111111010 !
b11100000000000000011111101111111111111111100000001111111010 n
b11100000000000000011111101111111111111111100000001111111010 w
b11100000000000000011111101111111111111111100000001111111010 x
b1 q
0]
b1111100111111011000000000000011000000000111110001111101100000000 \
b1111100111111011000000000000011000000000111110001111101100000000 `
b1111100111111011000000000000011000000000111110001111101100000000 "
b1111100111111011000000000000011000000000111110001111101100000000 U
b1111100111111011000000000000011000000000111110001111101100000000 m
b1111100111111011000000000000011000000000111110001111101100000000 ^
b1111100111111011000000000000011000000000111110001111101100000000 _
b1 Y
b11000000110000001110000011100000011111110101111100100000100 #
b11000000110000001110000011100000011111110101111100100000100 <
b11000000110000001110000011100000011111110101111100100000100 T
b11000000110000001110000011100000011111110101111100100000100 E
b11000000110000001110000011100000011111110101111100100000100 F
b1 A
b0 )
b0 9
b0 Q
b0 B
b1111101 &
b1111101 :
b1111101 =
b1111101 H
b1111111111001111 P
b0 N
b1111111111100010 M
b0 L
b10000 K
b1111111111110001 J
b0 I
b0 2
b11 5
1-
#12000
0-
#13000
b1111111111111110110010 &
b1111111111111110110010 :
b1111111111111110110010 =
b1111111111111110110010 H
b101010 P
b111 N
b1111111111011101 M
b1111111111111101 L
b1100 K
b1111111111101011 J
b1111111111101000 I
b0 ?
b110001 i
b11001 h
b0 g
b100100 f
b0 e
b1000000 d
b11001 c
b0 b
b11000000110000001110000011100000011111110101111100100000100 "
b11000000110000001110000011100000011111110101111100100000100 U
b11000000110000001110000011100000011111110101111100100000100 m
b11000000110000001110000011100000011111110101111100100000100 ^
b11000000110000001110000011100000011111110101111100100000100 _
b1 Z
b0 (
b0 R
b0 j
b0 [
b10 p
b1111100111111011000000000000011000000000111110001111101100000000 !
b1111100111111011000000000000011000000000111110001111101100000000 n
b1111100111111011000000000000011000000000111110001111101100000000 w
b1111100111111011000000000000011000000000111110001111101100000000 x
b1 r
b1 2
1-
#14000
0-
#15000
0v
b11000000110000001110000011100000011111110101111100100000100 u
b11000000110000001110000011100000011111110101111100100000100 y
b11000000110000001110000011100000011111110101111100100000100 !
b11000000110000001110000011100000011111110101111100100000100 n
b11000000110000001110000011100000011111110101111100100000100 w
b11000000110000001110000011100000011111110101111100100000100 x
b1 s
b0 '
b0 k
b0 t
b0 X
b11000111 %
b11000111 S
b11000111 V
b11000111 a
b1111111111010110 i
b1111111111100010 h
b101010 f
b110000 d
b100011 c
b0 @
b1111111111111111101010 &
b1111111111111111101010 :
b1111111111111111101010 =
b1111111111111111101010 H
b10 2
1-
#16000
0-
#17000
b0 A
b110101 %
b110101 S
b110101 V
b110101 a
b0 Y
b100100 $"
b100100 #"
b110001 ""
b110001 !"
b1001 ~
b100100 }
b110001 |
b10000 {
b0 q
b11 2
1-
#18000
0-
#19000
b0 r
b100011000 $
b100011000 l
b100011000 o
b100011000 z
b0 Z
b100 2
1-
#20000
0-
#21000
b0 s
b101 2
1-
#22000
0-
#23000
b110 2
1-
#24000
0-
#25000
b111 2
1-
#26000
0-
#27000
b1000 2
1-
#28000
0-
#29000
b1001 2
1-
#30000
0-
#31000
b1010 2
1-
#32000
b10 .
b10 8
0-
#33000
b10 )
b10 9
b10 Q
b10 B
b0 5
1-
#34000
b1000000001000001101111111111111001111110110000011111111011 /
b1000000001000001101111111111111001111110110000011111111011 ;
0-
#35000
b10 (
b10 R
b10 j
b10 [
b1000000001000001101111111111111001111110110000011111111011 #
b1000000001000001101111111111111001111110110000011111111011 <
b1000000001000001101111111111111001111110110000011111111011 T
b1000000001000001101111111111111001111110110000011111111011 E
b1000000001000001101111111111111001111110110000011111111011 F
b10 ?
b1 5
1-
#36000
b1111110100000001000001001111110111111011111111100000011111111100 /
b1111110100000001000001001111110111111011111111100000011111111100 ;
0-
#37000
b1110 P
b110 N
b101 M
b111 L
b1010 K
b10101 J
b11110 I
b1111110100000001000001001111110111111011111111100000011111111100 #
b1111110100000001000001001111110111111011111111100000011111111100 <
b1111110100000001000001001111110111111011111111100000011111111100 T
b1111110100000001000001001111110111111011111111100000011111111100 E
b1111110100000001000001001111110111111011111111100000011111111100 F
b10 @
b1000000001000001101111111111111001111110110000011111111011 "
b1000000001000001101111111111111001111110110000011111111011 U
b1000000001000001101111111111111001111110110000011111111011 m
b1000000001000001101111111111111001111110110000011111111011 ^
b1000000001000001101111111111111001111110110000011111111011 _
b10 X
b10 '
b10 k
b10 t
b10 5
1-
#38000
b0 .
b0 8
b10000001010000000011111100111111001111111111111100 /
b10000001010000000011111100111111001111111111111100 ;
0-
#39000
1,
b1000000001000001101111111111111001111110110000011111111011 !
b1000000001000001101111111111111001111110110000011111111011 n
b1000000001000001101111111111111001111110110000011111111011 w
b1000000001000001101111111111111001111110110000011111111011 x
b10 q
b1111110100000001000001001111110111111011111111100000011111111100 "
b1111110100000001000001001111110111111011111111100000011111111100 U
b1111110100000001000001001111110111111011111111100000011111111100 m
b1111110100000001000001001111110111111011111111100000011111111100 ^
b1111110100000001000001001111110111111011111111100000011111111100 _
b10 Y
b1111111111110010 i
b1111111111111011 h
b1111111111111010 f
b101000 d
b1111111111011101 c
b10000001010000000011111100111111001111111111111100 #
b10000001010000000011111100111111001111111111111100 <
b10000001010000000011111100111111001111111111111100 T
b10000001010000000011111100111111001111111111111100 E
b10000001010000000011111100111111001111111111111100 F
b10 A
b0 )
b0 9
b0 Q
b0 B
b1011101 &
b1011101 :
b1011101 =
b1011101 H
b1111111111101011 P
b100 N
b1111 M
b101 L
b100 K
b11000 I
b0 2
b11 5
1-
#40000
0-
#41000
1+
b110100 &
b110100 :
b110100 =
b110100 H
b0 P
b101 N
b0 M
b100 L
b1000 K
b1111111111111101 J
b0 ?
b1111111111111111101100 %
b1111111111111111101100 S
b1111111111111111101100 V
b1111111111111111101100 a
b10101 i
b1111111111101110 f
b10000 d
b10000001010000000011111100111111001111111111111100 "
b10000001010000000011111100111111001111111111111100 U
b10000001010000000011111100111111001111111111111100 m
b10000001010000000011111100111111001111111111111100 ^
b10000001010000000011111100111111001111111111111100 _
b10 Z
b0 (
b0 R
b0 j
b0 [
b1100 $"
b110 #"
b101010 ""
b1111111111111001 !"
b1111111111101011 ~
b11110 }
b1111111111001111 |
b1111111111101100 {
b1111110100000001000001001111110111111011111111100000011111111100 !
b1111110100000001000001001111110111111011111111100000011111111100 n
b1111110100000001000001001111110111111011111111100000011111111100 w
b1111110100000001000001001111110111111011111111100000011111111100 x
b10 r
b1 2
1-
#42000
0-
#43000
1*
b10000001010000000011111100111111001111111111111100 !
b10000001010000000011111100111111001111111111111100 n
b10000001010000000011111100111111001111111111111100 w
b10000001010000000011111100111111001111111111111100 x
b10 s
b0 '
b0 k
b0 t
b1111111111111111111001 $
b1111111111111111111001 l
b1111111111111111111001 o
b1111111111111111111001 z
b1111111111101110 $"
b11100 ""
b1111111111101011 !"
b1111111111110001 ~
b1100 }
b1111111111110000 {
b0 X
b1111111111111111101011 %
b1111111111111111101011 S
b1111111111111111101011 V
b1111111111111111101011 a
b0 i
b1111111111110110 h
b0 f
b100000 d
b101 c
b0 @
b100110 &
b100110 :
b100110 =
b100110 H
b10 2
1-
#44000
0-
#45000
0,
b0 A
b11011 %
b11011 S
b11011 V
b11011 a
b0 Y
b1111111111111110110111 $
b1111111111111110110111 l
b1111111111111110110111 o
b1111111111111110110111 z
b0 $"
b1100 #"
b100011 ""
b0 !"
b1111111111110100 ~
b11000 }
b111 |
b0 q
b11 2
1-
#46000
0-
#47000
0+
b0 r
b110010 $
b110010 l
b110010 o
b110010 z
b0 Z
b100 2
1-
#48000
0-
#49000
0*
b0 s
b101 2
1-
#50000
0-
#51000
b110 2
1-
#52000
0-
#53000
b111 2
1-
#54000
0-
#55000
b1000 2
1-
#56000
0-
#57000
b1001 2
1-
#58000
0-
#59000
b1010 2
1-
