core/behavorial/mac_col/verilog/mac_8in.v
module mac_8in (out, a, b, clk, reset);

parameter bw = 8;
parameter bw_psum = 2*bw+6;
parameter pr = 8;

output reg signed [bw_psum-1:0] out;
input  [pr*bw-1:0] a;
input  [pr*bw-1:0] b;


reg		[2*bw-1:0]	product0	;
reg		[2*bw-1:0]	product1	;
reg		[2*bw-1:0]	product2	;
reg		[2*bw-1:0]	product3	;
reg		[2*bw-1:0]	product4	;
reg		[2*bw-1:0]	product5	;
reg		[2*bw-1:0]	product6	;
reg		[2*bw-1:0]	product7	;

always @ (posedge clk) begin
	if (reset) begin
		out <= 0;
		product0 <= 0;
		product1 <= 0;
		product2 <= 0;
		product3 <= 0;
		product4 <= 0;
		product5 <= 0;
		product6 <= 0;
		product7 <= 0;
	end
	else begin
		product0	<=	{{(bw){a[bw*	1	-1]}},	a[bw*	1	-1:bw*	0	]}	*	{{(bw){b[bw*	1	-1]}},	b[bw*	1	-1:	bw*	0	]};
		product1	<=	{{(bw){a[bw*	2	-1]}},	a[bw*	2	-1:bw*	1	]}	*	{{(bw){b[bw*	2	-1]}},	b[bw*	2	-1:	bw*	1	]};
		product2	<=	{{(bw){a[bw*	3	-1]}},	a[bw*	3	-1:bw*	2	]}	*	{{(bw){b[bw*	3	-1]}},	b[bw*	3	-1:	bw*	2	]};
		product3	<=	{{(bw){a[bw*	4	-1]}},	a[bw*	4	-1:bw*	3	]}	*	{{(bw){b[bw*	4	-1]}},	b[bw*	4	-1:	bw*	3	]};
		product4	<=	{{(bw){a[bw*	5	-1]}},	a[bw*	5	-1:bw*	4	]}	*	{{(bw){b[bw*	5	-1]}},	b[bw*	5	-1:	bw*	4	]};
		product5	<=	{{(bw){a[bw*	6	-1]}},	a[bw*	6	-1:bw*	5	]}	*	{{(bw){b[bw*	6	-1]}},	b[bw*	6	-1:	bw*	5	]};
		product6	<=	{{(bw){a[bw*	7	-1]}},	a[bw*	7	-1:bw*	6	]}	*	{{(bw){b[bw*	7	-1]}},	b[bw*	7	-1:	bw*	6	]};
		product7	<=	{{(bw){a[bw*	8	-1]}},	a[bw*	8	-1:bw*	7	]}	*	{{(bw){b[bw*	8	-1]}},	b[bw*	8	-1:	bw*	7	]};

		out <= 
				{{(4){product0[2*bw-1]}},product0	}
			+	{{(4){product1[2*bw-1]}},product1	}
			+	{{(4){product2[2*bw-1]}},product2	}
			+	{{(4){product3[2*bw-1]}},product3	}
			+	{{(4){product4[2*bw-1]}},product4	}
			+	{{(4){product5[2*bw-1]}},product5	}
			+	{{(4){product6[2*bw-1]}},product6	}
			+	{{(4){product7[2*bw-1]}},product7	};
	end
end








endmodule

core/behavorial/mac_col/verilog/mac_col.v
module mac_col (clk, reset, out, q_in, q_out, i_inst, fifo_wr, o_inst);

parameter bw = 8;
parameter bw_psum = 2*bw+6;
parameter pr = 8;
parameter col_id = 0;

output signed [bw_psum-1:0] out;
input  signed [pr*bw-1:0] q_in;
output signed [pr*bw-1:0] q_out;
input  clk, reset;
input  [1:0] i_inst; // [1]: execute, [0]: load 
output [1:0] o_inst; // [1]: execute, [0]: load 
output fifo_wr;
reg    load_ready_q;
reg    [3:0] cnt_q;
reg    [1:0] inst_q;
reg    [1:0] inst_2q;
reg   signed [pr*bw-1:0] query_q;
reg   signed [pr*bw-1:0] key_q;
wire  signed [bw_psum-1:0] psum;

assign o_inst = inst_q;
assign fifo_wr = inst_2q[1];
assign q_out  = query_q;
assign out = psum;

mac_8in #(.bw(8), .bw_psum(19), .pr(8)) mac_8in_instance (
  .a(query_q), 
  .b(key_q),
  .out(psum),
  .clk(clk),
  .reset(reset)
); 


always @ (posedge clk) begin

  if (reset) begin

    cnt_q <= 0;
    load_ready_q <= 1;
    inst_q <= 0;
    inst_2q <= 0;

  end

  else begin

    inst_q <= i_inst;
    inst_2q <= inst_q;

    if (inst_q[0]) begin //load

       query_q <= q_in;

       if (cnt_q == col_id && load_ready_q) begin
         key_q <= q_in;
         load_ready_q <= 0;
       end

       else if (load_ready_q)
         cnt_q <= cnt_q + 1;
    end

    else if(inst_q[1]) begin
      query_q <= q_in;
    end

  end
end

endmodule

core/behavorial/mac_array/verilog/mac_col_tb.v
`timescale 1ns/1ps

module mac_col_tb;

reg clk = 0;
reg reset = 1;
reg [63:0] q_in = 0;
reg [1:0] i_inst = 0;

wire [31:0] out_0;
wire [63:0] q_out_0;
wire [1:0] o_inst_0;
wire fifo_wr_0;

wire [31:0] out_1;
wire [63:0] q_out_1;
wire [1:0] o_inst_1;
wire fifo_wr_1;

wire [31:0] out_2;
wire [63:0] q_out_2;
wire [1:0] o_inst_2;
wire fifo_wr_2;

parameter total_K = 3;
parameter total_Q = 3;

integer qk_file;
integer qk_scan_file;
integer  K[total_K-1:0][7:0];
integer  Q[total_Q-1:0][7:0];
integer  pred_result[total_K-1:0][total_Q-1:0];
//integer  result[total_cycle-1:0];
//integer  sum[total_cycle-1:0];

integer  captured_data;
`define NULL 0

integer i,j,k,t,p,q,s,u,m;


mac_col #(.bw(8), .bw_psum(32), .pr(8), .col_id(0)) mac_col_instance_0 (
      .clk(clk),
      .reset(reset),
      .out(out_0),
      .q_in(q_in),
      .q_out(q_out_0),
      .i_inst(i_inst),
      .o_inst(o_inst_0),
      .fifo_wr(fifo_wr_0)
);

mac_col #(.bw(8), .bw_psum(32), .pr(8), .col_id(1)) mac_col_instance_1 (
      .clk(clk),
      .reset(reset),
      .out(out_1),
      .q_in(q_out_0),
      .q_out(q_out_1),
      .i_inst(o_inst_0),
      .o_inst(o_inst_1),
      .fifo_wr(fifo_wr_1)
);

mac_col #(.bw(8), .bw_psum(32), .pr(8), .col_id(2)) mac_col_instance_2 (
      .clk(clk),
      .reset(reset),
      .out(out_2),
      .q_in(q_out_1),
      .q_out(q_out_2),
      .i_inst(o_inst_1),
      .o_inst(o_inst_2),
      .fifo_wr(fifo_wr_2)
);


initial begin 
      $dumpfile("mac_col_tb.vcd");
      $dumpvars(0, mac_col_tb);


      ///// Q data txt reading /////

      $display("##### Q data txt reading #####");


      qk_file = $fopen("qdata.txt", "r");

      for (q=0; q<total_Q; q=q+1) begin
            $display("Q vector: %d\n", q);
            for (j=0; j<8; j=j+1) begin
                  qk_scan_file = $fscanf(qk_file, "%d\n", captured_data);
                  Q[q][j] = captured_data;
                  $display("Data: %d\n", captured_data);
            end
      end
      /////////////////////////////////


      ///// K data txt reading /////

      $display("##### K data txt reading #####");


      qk_file = $fopen("kdata.txt", "r");

      for (q=0; q<total_K; q=q+1) begin
            $display("K vector: %d\n", q);
            for (j=0; j<8; j=j+1) begin
                  qk_scan_file = $fscanf(qk_file, "%d\n", captured_data);
                  K[q][j] = captured_data;
                  $display("Data: %d\n", captured_data);
            end
      end
      /////////////////////////////////


      ///// Predicted results calculation /////

      $display("##### K data txt reading #####");


      for (k=0; k<total_K; k=k+1) begin
            $display("K#: %d", k);
            for (q=0; q<total_Q; q=q+1) begin
                  $display("Q#: %d", q);
                  pred_result[k][q] = 0;
                  for (i=0; i<8; i=i+1) begin
                        pred_result[k][q] = pred_result[k][q] + Q[q][i]*K[k][i];
                  end
                  $display("Predicted psum: %d", pred_result[k][q]);
            end
      end
      /////////////////////////////////


      #1 clk = 1;
      #1 clk = 0; reset = 0;
      #1 clk = 1;
      #1 clk = 0; i_inst = 2'b01;
      #1 clk = 1;
      for (q=0; q<total_K; q=q+1) begin
            #1 clk = 0; q_in = {K[q][7][7:0], K[q][6][7:0], K[q][5][7:0], K[q][4][7:0], K[q][3][7:0], K[q][2][7:0], K[q][1][7:0], K[q][0][7:0]};
            if (q + 1 == total_K)
                  i_inst = 2'b00;
            #1 clk = 1;
      end

      for (i = 0; i < 10; i = i + 1) begin
            #1 clk = 0;
            #1 clk = 1;
      end

      #1 clk = 0; i_inst = 2'b10;
      #1 clk = 1;

      for (q=0; q<total_Q; q=q+1) begin
            #1 clk = 0; q_in = {Q[q][7][7:0], Q[q][6][7:0], Q[q][5][7:0], Q[q][4][7:0], Q[q][3][7:0], Q[q][2][7:0], Q[q][1][7:0], Q[q][0][7:0]};
            if (q + 1 == total_K)
                  i_inst = 2'b00;
            #1 clk = 1;
      end

      for (i = 0; i < 10; i = i + 1) begin
            #1 clk = 0;
            #1 clk = 1;
      end

      #1 $display("Finished.");
      #1 $finish;
end

endmodule

core/behavorial/mac_array/mac_col_tb.vcd
$date
	Wed Mar  5 20:29:52 2025
$end
$version
	Icarus Verilog
$end
$timescale
	1ps
$end
$scope module mac_col_tb $end
$var wire 64 ! q_out_2 [63:0] $end
$var wire 64 " q_out_1 [63:0] $end
$var wire 64 # q_out_0 [63:0] $end
$var wire 32 $ out_2 [31:0] $end
$var wire 32 % out_1 [31:0] $end
$var wire 32 & out_0 [31:0] $end
$var wire 2 ' o_inst_2 [1:0] $end
$var wire 2 ( o_inst_1 [1:0] $end
$var wire 2 ) o_inst_0 [1:0] $end
$var wire 1 * fifo_wr_2 $end
$var wire 1 + fifo_wr_1 $end
$var wire 1 , fifo_wr_0 $end
$var reg 1 - clk $end
$var reg 2 . i_inst [1:0] $end
$var reg 64 / q_in [63:0] $end
$var reg 1 0 reset $end
$var integer 32 1 captured_data [31:0] $end
$var integer 32 2 i [31:0] $end
$var integer 32 3 j [31:0] $end
$var integer 32 4 k [31:0] $end
$var integer 32 5 q [31:0] $end
$var integer 32 6 qk_file [31:0] $end
$var integer 32 7 qk_scan_file [31:0] $end
$scope module mac_col_instance_0 $end
$var wire 1 - clk $end
$var wire 2 8 i_inst [1:0] $end
$var wire 2 9 o_inst [1:0] $end
$var wire 32 : out [31:0] $end
$var wire 64 ; q_in [63:0] $end
$var wire 64 < q_out [63:0] $end
$var wire 1 0 reset $end
$var wire 32 = psum [31:0] $end
$var wire 1 , fifo_wr $end
$var reg 4 > cnt_q [3:0] $end
$var reg 2 ? inst_2q [1:0] $end
$var reg 2 @ inst_q [1:0] $end
$var reg 64 A key_q [63:0] $end
$var reg 1 B load_ready_q $end
$var reg 64 C query_q [63:0] $end
$scope module mac_8in_instance $end
$var wire 64 D a [63:0] $end
$var wire 64 E b [63:0] $end
$var wire 16 F product7 [15:0] $end
$var wire 16 G product6 [15:0] $end
$var wire 16 H product5 [15:0] $end
$var wire 16 I product4 [15:0] $end
$var wire 16 J product3 [15:0] $end
$var wire 16 K product2 [15:0] $end
$var wire 16 L product1 [15:0] $end
$var wire 16 M product0 [15:0] $end
$var wire 19 N out [18:0] $end
$upscope $end
$upscope $end
$scope module mac_col_instance_1 $end
$var wire 1 - clk $end
$var wire 2 O i_inst [1:0] $end
$var wire 2 P o_inst [1:0] $end
$var wire 32 Q out [31:0] $end
$var wire 64 R q_in [63:0] $end
$var wire 64 S q_out [63:0] $end
$var wire 1 0 reset $end
$var wire 32 T psum [31:0] $end
$var wire 1 + fifo_wr $end
$var reg 4 U cnt_q [3:0] $end
$var reg 2 V inst_2q [1:0] $end
$var reg 2 W inst_q [1:0] $end
$var reg 64 X key_q [63:0] $end
$var reg 1 Y load_ready_q $end
$var reg 64 Z query_q [63:0] $end
$scope module mac_8in_instance $end
$var wire 64 [ a [63:0] $end
$var wire 64 \ b [63:0] $end
$var wire 16 ] product7 [15:0] $end
$var wire 16 ^ product6 [15:0] $end
$var wire 16 _ product5 [15:0] $end
$var wire 16 ` product4 [15:0] $end
$var wire 16 a product3 [15:0] $end
$var wire 16 b product2 [15:0] $end
$var wire 16 c product1 [15:0] $end
$var wire 16 d product0 [15:0] $end
$var wire 19 e out [18:0] $end
$upscope $end
$upscope $end
$scope module mac_col_instance_2 $end
$var wire 1 - clk $end
$var wire 2 f i_inst [1:0] $end
$var wire 2 g o_inst [1:0] $end
$var wire 32 h out [31:0] $end
$var wire 64 i q_in [63:0] $end
$var wire 64 j q_out [63:0] $end
$var wire 1 0 reset $end
$var wire 32 k psum [31:0] $end
$var wire 1 * fifo_wr $end
$var reg 4 l cnt_q [3:0] $end
$var reg 2 m inst_2q [1:0] $end
$var reg 2 n inst_q [1:0] $end
$var reg 64 o key_q [63:0] $end
$var reg 1 p load_ready_q $end
$var reg 64 q query_q [63:0] $end
$scope module mac_8in_instance $end
$var wire 64 r a [63:0] $end
$var wire 64 s b [63:0] $end
$var wire 16 t product7 [15:0] $end
$var wire 16 u product6 [15:0] $end
$var wire 16 v product5 [15:0] $end
$var wire 16 w product4 [15:0] $end
$var wire 16 x product3 [15:0] $end
$var wire 16 y product2 [15:0] $end
$var wire 16 z product1 [15:0] $end
$var wire 16 { product0 [15:0] $end
$var wire 19 | out [18:0] $end
$upscope $end
$upscope $end
$upscope $end
$enddefinitions $end
#0
$dumpvars
bx |
bx {
bx z
bx y
bx x
bx w
bx v
bx u
bx t
bx s
bx r
bx q
xp
bx o
bx n
bx m
bx l
bx k
bx j
bx i
bx h
bx g
bx f
bx e
bx d
bx c
bx b
bx a
bx `
bx _
bx ^
bx ]
bx \
bx [
bx Z
xY
bx X
bx W
bx V
bx U
bx T
bx S
bx R
bx Q
bx P
bx O
bx N
bx M
bx L
bx K
bx J
bx I
bx H
bx G
bx F
bx E
bx D
bx C
xB
bx A
bx @
bx ?
bx >
bx =
bx <
b0 ;
bx :
bx 9
b0 8
b1 7
b10000000000000000000000000000100 6
b11 5
b11 4
b1000 3
b1000 2
b110 1
10
b0 /
b0 .
0-
x,
x+
x*
bx )
bx (
bx '
bx &
bx %
bx $
bx #
bx "
bx !
$end
#1000
0,
0+
0*
b0 ?
b0 )
b0 9
b0 O
b0 @
1B
b0 >
b0 V
b0 (
b0 P
b0 f
b0 W
1Y
b0 U
b0 m
b0 '
b0 g
b0 n
1p
b0 l
1-
#2000
00
0-
#3000
1-
#4000
b1 .
b1 8
0-
#5000
b1 )
b1 9
b1 O
b1 @
b0 5
1-
#6000
b11100000000000000011111101111111111111111100000001111111010 /
b11100000000000000011111101111111111111111100000001111111010 ;
0-
#7000
b1111101 &
b1111101 :
b1111101 =
b1111101 N
b100100 M
b1001 L
b100 K
b1 J
b11001 I
b1 H
b0 G
b110001 F
b1 (
b1 P
b1 f
b1 W
0B
b11100000000000000011111101111111111111111100000001111111010 A
b11100000000000000011111101111111111111111100000001111111010 E
b11100000000000000011111101111111111111111100000001111111010 #
b11100000000000000011111101111111111111111100000001111111010 <
b11100000000000000011111101111111111111111100000001111111010 R
b11100000000000000011111101111111111111111100000001111111010 C
b11100000000000000011111101111111111111111100000001111111010 D
b1 ?
b1 5
1-
#8000
b1111100111111011000000000000011000000000111110001111101100000000 /
b1111100111111011000000000000011000000000111110001111101100000000 ;
0-
#9000
b11111111111111111111111110110010 &
b11111111111111111111111110110010 :
b11111111111111111111111110110010 =
b1111111111110110010 N
b0 M
b1111111111110001 L
b10000 K
b0 J
b1111111111100010 I
b0 H
b1111111111001111 F
b1111100111111011000000000000011000000000111110001111101100000000 #
b1111100111111011000000000000011000000000111110001111101100000000 <
b1111100111111011000000000000011000000000111110001111101100000000 R
b1111100111111011000000000000011000000000111110001111101100000000 C
b1111100111111011000000000000011000000000111110001111101100000000 D
b1 U
b11100000000000000011111101111111111111111100000001111111010 "
b11100000000000000011111101111111111111111100000001111111010 S
b11100000000000000011111101111111111111111100000001111111010 i
b11100000000000000011111101111111111111111100000001111111010 Z
b11100000000000000011111101111111111111111100000001111111010 [
b1 V
b1 '
b1 g
b1 n
b10 5
1-
#10000
b0 .
b0 8
b11000000110000001110000011100000011111110101111100100000100 /
b11000000110000001110000011100000011111110101111100100000100 ;
0-
#11000
b11000111 %
b11000111 Q
b11000111 T
b11000111 e
b11111111111111111111111111101010 &
b11111111111111111111111111101010 :
b11111111111111111111111111101010 =
b1111111111111101010 N
b0 d
b11001 c
b1000000 b
b0 a
b100100 `
b0 _
b11001 ^
b110001 ]
b1111111111101000 M
b1111111111101011 L
b1100 K
b1111111111111101 J
b1111111111011101 I
b111 H
b101010 F
b1 l
b11100000000000000011111101111111111111111100000001111111010 !
b11100000000000000011111101111111111111111100000001111111010 j
b11100000000000000011111101111111111111111100000001111111010 q
b11100000000000000011111101111111111111111100000001111111010 r
b1 m
0Y
b1111100111111011000000000000011000000000111110001111101100000000 X
b1111100111111011000000000000011000000000111110001111101100000000 \
b1111100111111011000000000000011000000000111110001111101100000000 "
b1111100111111011000000000000011000000000111110001111101100000000 S
b1111100111111011000000000000011000000000111110001111101100000000 i
b1111100111111011000000000000011000000000111110001111101100000000 Z
b1111100111111011000000000000011000000000111110001111101100000000 [
b11000000110000001110000011100000011111110101111100100000100 #
b11000000110000001110000011100000011111110101111100100000100 <
b11000000110000001110000011100000011111110101111100100000100 R
b11000000110000001110000011100000011111110101111100100000100 C
b11000000110000001110000011100000011111110101111100100000100 D
b0 )
b0 9
b0 O
b0 @
b0 2
b11 5
1-
#12000
0-
#13000
b110101 %
b110101 Q
b110101 T
b110101 e
b100011 c
b110000 b
b101010 `
b1111111111100010 ^
b1111111111010110 ]
b0 ?
b11000000110000001110000011100000011111110101111100100000100 "
b11000000110000001110000011100000011111110101111100100000100 S
b11000000110000001110000011100000011111110101111100100000100 i
b11000000110000001110000011100000011111110101111100100000100 Z
b11000000110000001110000011100000011111110101111100100000100 [
b0 (
b0 P
b0 f
b0 W
b10 l
b1111100111111011000000000000011000000000111110001111101100000000 !
b1111100111111011000000000000011000000000111110001111101100000000 j
b1111100111111011000000000000011000000000111110001111101100000000 q
b1111100111111011000000000000011000000000111110001111101100000000 r
1-
#14000
b1 2
0-
#16000
b100011000 $
b100011000 h
b100011000 k
b100011000 |
b10000 {
b110001 z
b100100 y
b1001 x
b110001 w
b110001 v
b100100 u
b100100 t
0p
b11000000110000001110000011100000011111110101111100100000100 o
b11000000110000001110000011100000011111110101111100100000100 s
b11000000110000001110000011100000011111110101111100100000100 !
b11000000110000001110000011100000011111110101111100100000100 j
b11000000110000001110000011100000011111110101111100100000100 q
b11000000110000001110000011100000011111110101111100100000100 r
b0 '
b0 g
b0 n
b0 V
1-
#17000
b10 2
0-
#19000
b0 m
1-
#20000
b11 2
0-
#22000
1-
#23000
b100 2
0-
#25000
1-
#26000
b101 2
0-
#28000
1-
#29000
b110 2
0-
#31000
1-
#32000
b111 2
0-
#34000
1-
#35000
b1000 2
0-
#37000
1-
#38000
b1001 2
0-
#40000
1-
#41000
b1010 2
0-
#42000
1-
#43000
b10 .
b10 8
0-
#44000
b10 )
b10 9
b10 O
b10 @
b0 5
1-
#45000
b1000000001000001101111111111111001111110110000011111111011 /
b1000000001000001101111111111111001111110110000011111111011 ;
0-
#46000
b1011101 &
b1011101 :
b1011101 =
b1011101 N
b11110 M
b10101 L
b1010 K
b111 J
b101 I
b110 H
b1110 F
1,
b1000000001000001101111111111111001111110110000011111111011 #
b1000000001000001101111111111111001111110110000011111111011 <
b1000000001000001101111111111111001111110110000011111111011 R
b1000000001000001101111111111111001111110110000011111111011 C
b1000000001000001101111111111111001111110110000011111111011 D
b10 ?
b10 (
b10 P
b10 f
b10 W
b1 5
1-
#47000
b1111110100000001000001001111110111111011111111100000011111111100 /
b1111110100000001000001001111110111111011111111100000011111111100 ;
0-
#48000
b11111111111111111111111111101100 %
b11111111111111111111111111101100 Q
b11111111111111111111111111101100 T
b1111111111111101100 e
b110100 &
b110100 :
b110100 =
b110100 N
b1111111111011101 c
b101000 b
b1111111111111010 `
b1111111111111011 ^
b1111111111110010 ]
1+
b11000 M
b100 K
b101 J
b1111 I
b100 H
b1111111111101011 F
b10 '
b10 g
b10 n
b1000000001000001101111111111111001111110110000011111111011 "
b1000000001000001101111111111111001111110110000011111111011 S
b1000000001000001101111111111111001111110110000011111111011 i
b1000000001000001101111111111111001111110110000011111111011 Z
b1000000001000001101111111111111001111110110000011111111011 [
b10 V
b1111110100000001000001001111110111111011111111100000011111111100 #
b1111110100000001000001001111110111111011111111100000011111111100 <
b1111110100000001000001001111110111111011111111100000011111111100 R
b1111110100000001000001001111110111111011111111100000011111111100 C
b1111110100000001000001001111110111111011111111100000011111111100 D
b10 5
1-
#49000
b0 .
b0 8
b10000001010000000011111100111111001111111111111100 /
b10000001010000000011111100111111001111111111111100 ;
0-
#50000
b100110 &
b100110 :
b100110 =
b100110 N
b11111111111111111111111111101011 %
b11111111111111111111111111101011 Q
b11111111111111111111111111101011 T
b1111111111111101011 e
b11111111111111111111111111111001 $
b11111111111111111111111111111001 h
b11111111111111111111111111111001 k
b1111111111111111001 |
b1111111111111101 L
b1000 K
b100 J
b0 I
b101 H
b0 F
b10000 b
b1111111111101110 `
b10101 ]
b1111111111101100 {
b1111111111001111 z
b11110 y
b1111111111101011 x
b1111111111111001 w
b101010 v
b110 u
b1100 t
1*
b10000001010000000011111100111111001111111111111100 #
b10000001010000000011111100111111001111111111111100 <
b10000001010000000011111100111111001111111111111100 R
b10000001010000000011111100111111001111111111111100 C
b10000001010000000011111100111111001111111111111100 D
b0 )
b0 9
b0 O
b0 @
b1111110100000001000001001111110111111011111111100000011111111100 "
b1111110100000001000001001111110111111011111111100000011111111100 S
b1111110100000001000001001111110111111011111111100000011111111100 i
b1111110100000001000001001111110111111011111111100000011111111100 Z
b1111110100000001000001001111110111111011111111100000011111111100 [
b1000000001000001101111111111111001111110110000011111111011 !
b1000000001000001101111111111111001111110110000011111111011 j
b1000000001000001101111111111111001111110110000011111111011 q
b1000000001000001101111111111111001111110110000011111111011 r
b10 m
b0 2
b11 5
1-
#51000
0-
#52000
b11111111111111111111111110110111 $
b11111111111111111111111110110111 h
b11111111111111111111111110110111 k
b1111111111110110111 |
b11011 %
b11011 Q
b11011 T
b11011 e
b1111111111110000 {
b1100 y
b1111111111110001 x
b1111111111101011 w
b11100 v
b1111111111101110 t
b101 c
b100000 b
b0 `
b1111111111110110 ^
b0 ]
0,
b1111110100000001000001001111110111111011111111100000011111111100 !
b1111110100000001000001001111110111111011111111100000011111111100 j
b1111110100000001000001001111110111111011111111100000011111111100 q
b1111110100000001000001001111110111111011111111100000011111111100 r
b10000001010000000011111100111111001111111111111100 "
b10000001010000000011111100111111001111111111111100 S
b10000001010000000011111100111111001111111111111100 i
b10000001010000000011111100111111001111111111111100 Z
b10000001010000000011111100111111001111111111111100 [
b0 (
b0 P
b0 f
b0 W
b0 ?
1-
#53000
b1 2
0-
#55000
b110010 $
b110010 h
b110010 k
b110010 |
0+
b111 z
b11000 y
b1111111111110100 x
b0 w
b100011 v
b1100 u
b0 t
b0 V
b10000001010000000011111100111111001111111111111100 !
b10000001010000000011111100111111001111111111111100 j
b10000001010000000011111100111111001111111111111100 q
b10000001010000000011111100111111001111111111111100 r
b0 '
b0 g
b0 n
1-
#56000
b10 2
0-
#58000
0*
b0 m
1-
#59000
b11 2
0-
#61000
1-
#62000
b100 2
0-
#64000
1-
#65000
b101 2
0-
#67000
1-
#68000
b110 2
0-
#70000
1-
#71000
b111 2
0-
#73000
1-
#74000
b1000 2
0-
#76000
1-
#77000
b1001 2
0-
#79000
1-
#80000
b1010 2
0-
