core/behavorial/mac_array/verilog/mac_8in.v
module mac_8in (out, a, b, clk, reset);

parameter bw = 8;
parameter bw_psum = 2*bw+6;
parameter pr = 8;

output reg signed [bw_psum-1:0] out;
input  [pr*bw-1:0] a;
input  [pr*bw-1:0] b;
input clk;
input reset;


reg signed		[2*bw-1:0]	product0	;
reg signed		[2*bw-1:0]	product1	;
reg signed		[2*bw-1:0]	product2	;
reg signed		[2*bw-1:0]	product3	;
reg signed		[2*bw-1:0]	product4	;
reg signed		[2*bw-1:0]	product5	;
reg signed		[2*bw-1:0]	product6	;
reg signed		[2*bw-1:0]	product7	;

always @ (posedge clk) begin
	if (reset) begin
		out <= 0;
		product0 <= 0;
		product1 <= 0;
		product2 <= 0;
		product3 <= 0;
		product4 <= 0;
		product5 <= 0;
		product6 <= 0;
		product7 <= 0;
	end
	else begin
		product0	<=	{{(bw){a[bw*	1	-1]}},	a[bw*	1	-1:bw*	0	]}	*	{{(bw){b[bw*	1	-1]}},	b[bw*	1	-1:	bw*	0	]};
		product1	<=	{{(bw){a[bw*	2	-1]}},	a[bw*	2	-1:bw*	1	]}	*	{{(bw){b[bw*	2	-1]}},	b[bw*	2	-1:	bw*	1	]};
		product2	<=	{{(bw){a[bw*	3	-1]}},	a[bw*	3	-1:bw*	2	]}	*	{{(bw){b[bw*	3	-1]}},	b[bw*	3	-1:	bw*	2	]};
		product3	<=	{{(bw){a[bw*	4	-1]}},	a[bw*	4	-1:bw*	3	]}	*	{{(bw){b[bw*	4	-1]}},	b[bw*	4	-1:	bw*	3	]};
		product4	<=	{{(bw){a[bw*	5	-1]}},	a[bw*	5	-1:bw*	4	]}	*	{{(bw){b[bw*	5	-1]}},	b[bw*	5	-1:	bw*	4	]};
		product5	<=	{{(bw){a[bw*	6	-1]}},	a[bw*	6	-1:bw*	5	]}	*	{{(bw){b[bw*	6	-1]}},	b[bw*	6	-1:	bw*	5	]};
		product6	<=	{{(bw){a[bw*	7	-1]}},	a[bw*	7	-1:bw*	6	]}	*	{{(bw){b[bw*	7	-1]}},	b[bw*	7	-1:	bw*	6	]};
		product7	<=	{{(bw){a[bw*	8	-1]}},	a[bw*	8	-1:bw*	7	]}	*	{{(bw){b[bw*	8	-1]}},	b[bw*	8	-1:	bw*	7	]};

		out <= product0 + product1 + product2 + product3 + product4 + product5 + product6 + product7;

	end
end








endmodule

core/behavorial/mac_array/verilog/mac_col.v
module mac_col (clk, reset, out, q_in, q_out, i_inst, fifo_wr, o_inst);

parameter bw = 8;
parameter bw_psum = 2*bw+6;
parameter pr = 8;
parameter col_id = 0;

output signed [bw_psum-1:0] out;
input  signed [pr*bw-1:0] q_in;
output signed [pr*bw-1:0] q_out;
input  clk, reset;
input  [1:0] i_inst; // [1]: execute, [0]: load 
output [1:0] o_inst; // [1]: execute, [0]: load 
output fifo_wr;
reg    load_ready_q;
reg    [3:0] cnt_q;
reg    [1:0] inst_q;
reg    [1:0] inst_2q;
reg    [1:0] inst_3q;
reg    [1:0] inst_4q;
reg   signed [pr*bw-1:0] query_q;
reg   signed [pr*bw-1:0] key_q;
wire [bw_psum-1:0] psum;

assign o_inst = inst_q;
assign fifo_wr = inst_4q[1];
assign q_out  = query_q;
assign out = psum;

mac_8in #(.bw(8), .bw_psum(bw_psum), .pr(8)) mac_8in_instance (
  .a(query_q), 
  .b(key_q),
  .out(psum),
  .clk(clk),
  .reset(reset)
); 


always @ (posedge clk) begin

  if (reset) begin

    cnt_q <= 0;
    load_ready_q <= 1;
    inst_q <= 0;
    inst_2q <= 0;
    inst_3q <= 0;
    inst_4q <= 0;

  end

  else begin

    inst_q <= i_inst;
    inst_2q <= inst_q;
    inst_3q <= inst_2q;
    inst_4q <= inst_3q;

    if (inst_q[0]) begin //load

       query_q <= q_in;

       if (cnt_q == col_id && load_ready_q) begin
         key_q <= q_in;
         load_ready_q <= 0;
       end

       else if (load_ready_q)
         cnt_q <= cnt_q + 1;
    end

    else if(inst_q[1]) begin
      query_q <= q_in;
    end

  end
end

endmodule

core/behavorial/mac_array/verilog/mac_array.v
module mac_array (clk, reset, in, out, fifo_wr, inst);

parameter col = 8;
parameter bw = 8;
parameter bw_psum = 2*bw+6;
parameter pr = 8;

output [bw_psum*col-1:0] out;
input  [pr*bw-1:0] in;
input  clk, reset;
input  [1:0] inst; // [1]: execute, [0]: load 
output [col-1:0] fifo_wr;

wire   [col*bw_psum-1:0] psum;
wire   [2*(col+1)-1:0] inst_temp;
wire   [2*(col+1)*bw*pr-1:0] q_temp;


assign inst_temp[1:0]    = inst;
assign q_temp[bw*pr-1:0] = in;

for (i=0; i<col ; i=i+1) begin

   mac_col #(.bw(bw), .bw_psum(bw_psum), .pr(pr), .col_id(i)) mac_col_inst (
        .q_in( q_temp[pr*bw*(i+1)-1    :pr*bw*(i)]), 
        .q_out(q_temp[pr*bw*(i+2)-1:pr*bw*(i+1)]), 
        .clk(clk), 
        .reset(reset), 
        .fifo_wr(fifo_wr[i]),
        .i_inst(inst_temp[2*(i+1)-1:2*(i)]),     
        .o_inst(inst_temp[2*(i+2)-1:2*(i+1)]),     
	    .out(out[bw_psum*(i+1)-1 : bw_psum*(i)])
   );
   
end 

endmodule

core/behavorial/mac_array/verilog/mac_array_tb.v
`timescale 1ns/1ps

module mac_array_tb;

reg clk = 0;
reg reset = 1;
reg [63:0] q_in = 0;
reg [1:0] i_inst = 0;

parameter total_K = 1;
parameter total_Q = 8;

integer qk_file;
integer qk_scan_file;
integer  K[total_K-1:0][7:0];
integer  Q[total_Q-1:0][7:0];
integer  pred_result[total_K-1:0][total_Q-1:0];

integer  captured_data;
`define NULL 0

integer i,j,k,t,p,q,s,u,m;

wire [22*total_K-1:0] out;
wire [total_K-1:0] fifo_wr;


mac_array #(.col(total_K), .bw(8), .bw_psum(22), .pr(8)) DUT (
      .clk(clk),
      .reset(reset),
      .in(q_in),
      .out(out),
      .fifo_wr(fifo_wr),
      .inst(i_inst)
);

initial begin 
      $dumpfile("mac_array_tb.vcd");
      $dumpvars(0, mac_array_tb);


      ///// Q data txt reading /////

      $display("##### Q data txt reading #####");


      qk_file = $fopen("qdata.txt", "r");

      for (q=0; q<total_Q; q=q+1) begin
            $display("Q vector: %d\n", q);
            for (j=0; j<8; j=j+1) begin
                  qk_scan_file = $fscanf(qk_file, "%d\n", captured_data);
                  Q[q][j] = captured_data;
                  $display("Data: %d\n", captured_data);
            end
      end
      /////////////////////////////////


      ///// K data txt reading /////

      $display("##### K data txt reading #####");


      qk_file = $fopen("kdata.txt", "r");

      for (q=0; q<total_K; q=q+1) begin
            $display("K vector: %d\n", q);
            for (j=0; j<8; j=j+1) begin
                  qk_scan_file = $fscanf(qk_file, "%d\n", captured_data);
                  K[q][j] = captured_data;
                  $display("Data: %d\n", captured_data);
            end
      end
      /////////////////////////////////


      ///// Predicted results calculation /////

      $display("##### K data txt reading #####");


      for (k=0; k<total_K; k=k+1) begin
            $display("K#: %d", k);
            for (q=0; q<total_Q; q=q+1) begin
                  $display("Q#: %d", q);
                  pred_result[k][q] = 0;
                  for (i=0; i<8; i=i+1) begin
                        pred_result[k][q] = pred_result[k][q] + Q[q][i]*K[k][i];
                  end
                  $display("Predicted psum: %d", pred_result[k][q]);
            end
      end
      /////////////////////////////////


      #1 clk = 1;
      #1 clk = 0; reset = 0;
      #1 clk = 1;
      #1 clk = 0; i_inst = 2'b01;
      #1 clk = 1;
      for (q=0; q<total_K; q=q+1) begin
            #1 clk = 0; q_in = {K[q][7][7:0], K[q][6][7:0], K[q][5][7:0], K[q][4][7:0], K[q][3][7:0], K[q][2][7:0], K[q][1][7:0], K[q][0][7:0]};
            if (q + 1 == total_K)
                  i_inst = 2'b00;
            #1 clk = 1;
      end

      for (i = 0; i < total_K + total_Q + 5; i = i + 1) begin
            #1 clk = 0;
            #1 clk = 1;
      end

      #1 clk = 0; i_inst = 2'b10;
      #1 clk = 1;

      for (q=0; q<total_Q; q=q+1) begin
            #1 clk = 0; q_in = {Q[q][7][7:0], Q[q][6][7:0], Q[q][5][7:0], Q[q][4][7:0], Q[q][3][7:0], Q[q][2][7:0], Q[q][1][7:0], Q[q][0][7:0]};
            if (q + 1 == total_K)
                  i_inst = 2'b00;
            #1 clk = 1;
      end

      for (i = 0; i < total_K + total_Q + 5; i = i + 1) begin
            #1 clk = 0;
            #1 clk = 1;
      end

      #1 $display("Finished.");
      #1 $finish;
end

endmodule

core/behavorial/mac_array/mac_array_tb.vcd
$date
	Wed Mar  5 22:13:48 2025
$end
$version
	Icarus Verilog
$end
$timescale
	1ps
$end
$scope module mac_array_tb $end
$var wire 22 ! out [21:0] $end
$var wire 1 " fifo_wr $end
$var reg 1 # clk $end
$var reg 2 $ i_inst [1:0] $end
$var reg 64 % q_in [63:0] $end
$var reg 1 & reset $end
$var integer 32 ' captured_data [31:0] $end
$var integer 32 ( i [31:0] $end
$var integer 32 ) j [31:0] $end
$var integer 32 * k [31:0] $end
$var integer 32 + q [31:0] $end
$var integer 32 , qk_file [31:0] $end
$var integer 32 - qk_scan_file [31:0] $end
$scope module DUT $end
$var wire 1 # clk $end
$var wire 64 . in [63:0] $end
$var wire 2 / inst [1:0] $end
$var wire 1 & reset $end
$var wire 256 0 q_temp [255:0] $end
$var wire 22 1 out [21:0] $end
$var wire 4 2 inst_temp [3:0] $end
$var wire 1 " fifo_wr $end
$scope begin genblk1[0] $end
$scope module mac_col_inst $end
$var wire 1 # clk $end
$var wire 2 3 i_inst [1:0] $end
$var wire 2 4 o_inst [1:0] $end
$var wire 22 5 out [21:0] $end
$var wire 64 6 q_in [63:0] $end
$var wire 64 7 q_out [63:0] $end
$var wire 1 & reset $end
$var wire 22 8 psum [21:0] $end
$var wire 1 " fifo_wr $end
$var reg 4 9 cnt_q [3:0] $end
$var reg 2 : inst_2q [1:0] $end
$var reg 2 ; inst_3q [1:0] $end
$var reg 2 < inst_4q [1:0] $end
$var reg 2 = inst_q [1:0] $end
$var reg 64 > key_q [63:0] $end
$var reg 1 ? load_ready_q $end
$var reg 64 @ query_q [63:0] $end
$scope module mac_8in_instance $end
$var wire 64 A a [63:0] $end
$var wire 64 B b [63:0] $end
$var wire 1 # clk $end
$var wire 1 & reset $end
$var reg 22 C out [21:0] $end
$var reg 16 D product0 [15:0] $end
$var reg 16 E product1 [15:0] $end
$var reg 16 F product2 [15:0] $end
$var reg 16 G product3 [15:0] $end
$var reg 16 H product4 [15:0] $end
$var reg 16 I product5 [15:0] $end
$var reg 16 J product6 [15:0] $end
$var reg 16 K product7 [15:0] $end
$upscope $end
$upscope $end
$upscope $end
$upscope $end
$upscope $end
$enddefinitions $end
#0
$dumpvars
bx K
bx J
bx I
bx H
bx G
bx F
bx E
bx D
bx C
bx B
bx A
bx @
x?
bx >
bx =
bx <
bx ;
bx :
bx 9
bx 8
bx 7
b0 6
bx 5
bx 4
b0 3
bx00 2
bx 1
bzxxxxxxxxxxxxxxxxxxxxxxxxxxxxxxxxxxxxxxxxxxxxxxxxxxxxxxxxxxxxxxxx0000000000000000000000000000000000000000000000000000000000000000 0
b0 /
b0 .
b1 -
b10000000000000000000000000000100 ,
b1000 +
b1 *
b1000 )
b1000 (
b111 '
1&
b0 %
b0 $
0#
x"
bx !
$end
#1000
0"
b0 K
b0 J
b0 I
b0 H
b0 G
b0 F
b0 E
b0 D
b0 !
b0 1
b0 5
b0 8
b0 C
b0 <
b0 ;
b0 :
b0 2
b0 4
b0 =
1?
b0 9
1#
#2000
0&
0#
#3000
bx K
bx J
bx I
bx H
bx G
bx F
bx E
bx D
1#
#4000
b1 3
b1 2
b1 $
b1 /
0#
#5000
bx !
bx 1
bx 5
bx 8
bx C
b101 2
b1 4
b1 =
b0 +
1#
#6000
b0 3
b11100000000000000011111101111111111111111100000001111111010 6
b100 2
b0 $
b0 /
bzxxxxxxxxxxxxxxxxxxxxxxxxxxxxxxxxxxxxxxxxxxxxxxxxxxxxxxxxxxxxxxxx0000011100000000000000011111101111111111111111100000001111111010 0
b11100000000000000011111101111111111111111100000001111111010 %
b11100000000000000011111101111111111111111100000001111111010 .
0#
#7000
0?
b11100000000000000011111101111111111111111100000001111111010 >
b11100000000000000011111101111111111111111100000001111111010 B
bz00000111000000000000000111111011111111111111111000000011111110100000011100000000000000011111101111111111111111100000001111111010 0
b11100000000000000011111101111111111111111100000001111111010 7
b11100000000000000011111101111111111111111100000001111111010 @
b11100000000000000011111101111111111111111100000001111111010 A
b1 :
b0 2
b0 4
b0 =
b0 (
b1 +
1#
#8000
0#
#9000
b110001 K
b0 J
b1 I
b11001 H
b1 G
b100 F
b1001 E
b100100 D
b1 ;
b0 :
b1 (
1#
#10000
0#
#11000
b1 <
b0 ;
b1111101 !
b1111101 1
b1111101 5
b1111101 8
b1111101 C
b10 (
1#
#12000
0#
#13000
b0 <
b11 (
1#
#14000
0#
#15000
b100 (
1#
#16000
0#
#17000
b101 (
1#
#18000
0#
#19000
b110 (
1#
#20000
0#
#21000
b111 (
1#
#22000
0#
#23000
b1000 (
1#
#24000
0#
#25000
b1001 (
1#
#26000
0#
#27000
b1010 (
1#
#28000
0#
#29000
b1011 (
1#
#30000
0#
#31000
b1100 (
1#
#32000
0#
#33000
b1101 (
1#
#34000
0#
#35000
b1110 (
1#
#36000
b10 3
b10 2
b10 $
b10 /
0#
#37000
b1010 2
b10 4
b10 =
b0 +
1#
#38000
b1000000001000001101111111111111001111110110000011111111011 6
bz00000111000000000000000111111011111111111111111000000011111110100000001000000001000001101111111111111001111110110000011111111011 0
b1000000001000001101111111111111001111110110000011111111011 %
b1000000001000001101111111111111001111110110000011111111011 .
0#
#39000
bz00000010000000010000011011111111111110011111101100000111111110110000001000000001000001101111111111111001111110110000011111111011 0
b1000000001000001101111111111111001111110110000011111111011 7
b1000000001000001101111111111111001111110110000011111111011 @
b1000000001000001101111111111111001111110110000011111111011 A
b10 :
b1 +
1#
#40000
b1111110100000001000001001111110111111011111111100000011111111100 6
bz00000010000000010000011011111111111110011111101100000111111110111111110100000001000001001111110111111011111111100000011111111100 0
b1111110100000001000001001111110111111011111111100000011111111100 %
b1111110100000001000001001111110111111011111111100000011111111100 .
0#
#41000
b1110 K
b110 I
b101 H
b111 G
b1010 F
b10101 E
b11110 D
bz11111101000000010000010011111101111110111111111000000111111111001111110100000001000001001111110111111011111111100000011111111100 0
b1111110100000001000001001111110111111011111111100000011111111100 7
b1111110100000001000001001111110111111011111111100000011111111100 @
b1111110100000001000001001111110111111011111111100000011111111100 A
b10 ;
b10 +
1#
#42000
b10000001010000000011111100111111001111111111111100 6
bz11111101000000010000010011111101111110111111111000000111111111000000000000000010000001010000000011111100111111001111111111111100 0
b10000001010000000011111100111111001111111111111100 %
b10000001010000000011111100111111001111111111111100 .
0#
#43000
1"
bz00000000000000100000010100000000111111001111110011111111111111000000000000000010000001010000000011111100111111001111111111111100 0
b10000001010000000011111100111111001111111111111100 7
b10000001010000000011111100111111001111111111111100 @
b10000001010000000011111100111111001111111111111100 A
b10 <
b1011101 !
b1011101 1
b1011101 5
b1011101 8
b1011101 C
b1111111111101011 K
b100 I
b1111 H
b101 G
b100 F
b11000 D
b11 +
1#
#44000
b11000000001000000100000011011111100000001100000001111111101 6
bz00000000000000100000010100000000111111001111110011111111111111000000011000000001000000100000011011111100000001100000001111111101 0
b11000000001000000100000011011111100000001100000001111111101 %
b11000000001000000100000011011111100000001100000001111111101 .
0#
#45000
b100000000000000110100 !
b100000000000000110100 1
b100000000000000110100 5
b100000000000000110100 8
b100000000000000110100 C
b0 K
b101 I
b0 H
b100 G
b1000 F
b1111111111111101 E
bz00000110000000010000001000000110111111000000011000000011111111010000011000000001000000100000011011111100000001100000001111111101 0
b11000000001000000100000011011111100000001100000001111111101 7
b11000000001000000100000011011111100000001100000001111111101 @
b11000000001000000100000011011111100000001100000001111111101 A
b100 +
1#
#46000
b10011111101000000010000001000000110111111100000010111111000 6
bz00000110000000010000001000000110111111000000011000000011111111010000010011111101000000010000001000000110111111100000010111111000 0
b10011111101000000010000001000000110111111100000010111111000 %
b10011111101000000010000001000000110111111100000010111111000 .
0#
#47000
bz00000100111111010000000100000010000001101111111000000101111110000000010011111101000000010000001000000110111111100000010111111000 0
b10011111101000000010000001000000110111111100000010111111000 7
b10011111101000000010000001000000110111111100000010111111000 @
b10011111101000000010000001000000110111111100000010111111000 A
b100000000000000100110 !
b100000000000000100110 1
b100000000000000100110 5
b100000000000000100110 8
b100000000000000100110 C
b101010 K
b10 I
b1111111111100010 H
b1111111111110100 F
b1001 E
b10010 D
b101 +
1#
#48000
b1000000000000001001111111111111010111111101111111111111110 6
bz00000100111111010000000100000010000001101111111000000101111110000000001000000000000001001111111111111010111111101111111111111110 0
b1000000000000001001111111111111010111111101111111111111110 %
b1000000000000001001111111111111010111111101111111111111110 .
0#
#49000
b1000000000000000100001 !
b1000000000000000100001 1
b1000000000000000100001 5
b1000000000000000100001 8
b1000000000000000100001 C
b11100 K
b1 I
b1111111111110110 H
b1111111111111010 G
b100 F
b1111 E
b110000 D
bz00000010000000000000010011111111111110101111111011111111111111100000001000000000000001001111111111111010111111101111111111111110 0
b1000000000000001001111111111111010111111101111111111111110 7
b1000000000000001001111111111111010111111101111111111111110 @
b1000000000000001001111111111111010111111101111111111111110 A
b110 +
1#
#50000
b11011111001000000010000001000000011111111111111100100000101 6
bz00000010000000000000010011111111111110101111111011111111111111100000011011111001000000010000001000000011111111111111100100000101 0
b11011111001000000010000001000000011111111111111100100000101 %
b11011111001000000010000001000000011111111111111100100000101 .
0#
#51000
bz00000110111110010000000100000010000000111111111111111001000001010000011011111001000000010000001000000011111111111111100100000101 0
b11011111001000000010000001000000011111111111111100100000101 7
b11011111001000000010000001000000011111111111111100100000101 @
b11011111001000000010000001000000011111111111111100100000101 A
b1000000000000001010000 !
b1000000000000001010000 1
b1000000000000001010000 5
b1000000000000001010000 8
b1000000000000001010000 C
b1110 K
b100 I
b101 H
b110 G
b1111111111111101 E
b1100 D
b111 +
1#
#52000
b0 3
b1111111100000110111111100000000000000110111111011111100000000101 6
b1000 2
b0 $
b0 /
bz00000110111110010000000100000010000000111111111111111001000001011111111100000110111111100000000000000110111111011111100000000101 0
b1111111100000110111111100000000000000110111111011111100000000101 %
b1111111100000110111111100000000000000110111111011111100000000101 .
0#
#53000
b100000000000000101010 !
b100000000000000101010 1
b100000000000000101010 5
b100000000000000101010 8
b100000000000000101010 C
b101010 K
b1 I
b1111111111110110 H
b1111111111111101 G
b10 F
b1111111111101011 E
b1111111111100010 D
bz11111111000001101111111000000000000001101111110111111000000001011111111100000110111111100000000000000110111111011111100000000101 0
b1111111100000110111111100000000000000110111111011111100000000101 7
b1111111100000110111111100000000000000110111111011111100000000101 @
b1111111100000110111111100000000000000110111111011111100000000101 A
b0 2
b0 4
b0 =
b0 (
b1000 +
1#
#54000
0#
#55000
b0 :
b1111111111111111101101 !
b1111111111111111101101 1
b1111111111111111101101 5
b1111111111111111101101 8
b1111111111111111101101 C
b1111111111111001 K
b1111111111111110 I
b0 H
b1111111111111010 G
b110 F
b1111111111101000 E
b1 (
1#
#56000
0#
#57000
b11111111111111000001 !
b11111111111111000001 1
b11111111111111000001 5
b11111111111111000001 8
b11111111111111000001 C
b0 ;
b10 (
1#
#58000
0#
#59000
0"
b0 <
b11 (
1#
#60000
0#
#61000
b100 (
1#
#62000
0#
#63000
b101 (
1#
#64000
0#
#65000
b110 (
1#
#66000
0#
#67000
b111 (
1#
#68000
0#
#69000
b1000 (
1#
#70000
0#
#71000
b1001 (
1#
#72000
0#
#73000
b1010 (
1#
#74000
0#
#75000
b1011 (
1#
#76000
0#
#77000
b1100 (
1#
#78000
0#
#79000
b1101 (
1#
#80000
0#
#81000
b1110 (
1#
