single_core_hierarchical/core_syn/verilog/mac_8in.v
module mac_8in (out, a, b, clk, reset);

parameter bw = 8;
parameter bw_psum = 2*bw+6;
parameter pr = 8;

output reg signed [bw_psum-1:0] out;
input  [pr*bw-1:0] a;
input  [pr*bw-1:0] b;
input clk;
input reset;


reg signed		[2*bw-1:0]	product0	;
reg signed		[2*bw-1:0]	product1	;
reg signed		[2*bw-1:0]	product2	;
reg signed		[2*bw-1:0]	product3	;
reg signed		[2*bw-1:0]	product4	;
reg signed		[2*bw-1:0]	product5	;
reg signed		[2*bw-1:0]	product6	;
reg signed		[2*bw-1:0]	product7	;

reg signed [bw_psum-1:0] psum_0_0;
reg signed [bw_psum-1:0] psum_0_1;
reg signed [bw_psum-1:0] psum_0_2;
reg signed [bw_psum-1:0] psum_0_3;

reg signed [bw_psum-1:0] psum_1_0;
reg signed [bw_psum-1:0] psum_1_1;


always @ (posedge clk) begin
	if (reset) begin
		out <= 0;
		product0 <= 0;
		product1 <= 0;
		product2 <= 0;
		product3 <= 0;
		product4 <= 0;
		product5 <= 0;
		product6 <= 0;
		product7 <= 0;
	end
	else begin
		product0	<=	{{(bw){a[bw*	1	-1]}},	a[bw*	1	-1:bw*	0	]}	*	{{(bw){b[bw*	1	-1]}},	b[bw*	1	-1:	bw*	0	]};
		product1	<=	{{(bw){a[bw*	2	-1]}},	a[bw*	2	-1:bw*	1	]}	*	{{(bw){b[bw*	2	-1]}},	b[bw*	2	-1:	bw*	1	]};
		product2	<=	{{(bw){a[bw*	3	-1]}},	a[bw*	3	-1:bw*	2	]}	*	{{(bw){b[bw*	3	-1]}},	b[bw*	3	-1:	bw*	2	]};
		product3	<=	{{(bw){a[bw*	4	-1]}},	a[bw*	4	-1:bw*	3	]}	*	{{(bw){b[bw*	4	-1]}},	b[bw*	4	-1:	bw*	3	]};
		product4	<=	{{(bw){a[bw*	5	-1]}},	a[bw*	5	-1:bw*	4	]}	*	{{(bw){b[bw*	5	-1]}},	b[bw*	5	-1:	bw*	4	]};
		product5	<=	{{(bw){a[bw*	6	-1]}},	a[bw*	6	-1:bw*	5	]}	*	{{(bw){b[bw*	6	-1]}},	b[bw*	6	-1:	bw*	5	]};
		product6	<=	{{(bw){a[bw*	7	-1]}},	a[bw*	7	-1:bw*	6	]}	*	{{(bw){b[bw*	7	-1]}},	b[bw*	7	-1:	bw*	6	]};
		product7	<=	{{(bw){a[bw*	8	-1]}},	a[bw*	8	-1:bw*	7	]}	*	{{(bw){b[bw*	8	-1]}},	b[bw*	8	-1:	bw*	7	]};

		psum_0_0 <= product0 + product1;
		psum_0_1 <= product2 + product3;
		psum_0_2 <= product4 + product5;
		psum_0_3 <= product6 + product7;

		psum_1_0 <= psum_0_0 + psum_0_1;
		psum_1_1 <= psum_0_2 + psum_0_3;

		out <= psum_1_0 + psum_1_1;
		//out <= product0 + product1 + product2 + product3 + product4 + product5 + product6 + product7;

	end
end








endmodule

step_1/syn/verilog/mac_col.v
module mac_col (clk, reset, out, q_in, q_out, i_inst, fifo_wr, o_inst);

parameter bw = 8;
parameter bw_psum = 2*bw+6;
parameter pr = 8;
parameter col_id = 0;

output signed [bw_psum-1:0] out;
input  signed [pr*bw-1:0] q_in;
output signed [pr*bw-1:0] q_out;
input  clk, reset;
input  [1:0] i_inst; // [1]: execute, [0]: load 
output [1:0] o_inst; // [1]: execute, [0]: load 
output fifo_wr;
reg    load_ready_q;
reg    [3:0] cnt_q;
reg    [1:0] inst_q;
reg    [1:0] inst_2q;
reg    [1:0] inst_3q;
reg    [1:0] inst_4q;
reg    [1:0] inst_5q;
reg    [1:0] inst_6q;
reg   signed [pr*bw-1:0] query_q;
reg   signed [pr*bw-1:0] key_q;
wire [bw_psum-1:0] psum;

assign o_inst = inst_q;
assign fifo_wr = inst_6q[1];
assign q_out  = query_q;
assign out = psum;

mac_8in #(.bw(8), .bw_psum(bw_psum), .pr(8)) mac_8in_instance (
  .a(query_q), 
  .b(key_q),
  .out(psum),
  .clk(clk),
  .reset(reset)
); 


always @ (posedge clk or posedge reset) begin

  if (reset) begin

    cnt_q <= 0;
    load_ready_q <= 1;
    inst_q <= 0;
    inst_2q <= 0;
    inst_3q <= 0;
    inst_4q <= 0;
    inst_5q <= 0;
    inst_6q <= 0;
    key_q <= 0;
    query_q <= 0;

  end

  else begin

    inst_q <= i_inst;
    inst_2q <= inst_q;
    inst_3q <= inst_2q;
    inst_4q <= inst_3q;
    inst_5q <= inst_4q;
    inst_6q <= inst_5q;


    if (inst_q[0]) begin //load

       query_q <= q_in;

       if (cnt_q == col_id && load_ready_q) begin
         key_q <= q_in;
         load_ready_q <= 0;
       end

       else if (load_ready_q)
         cnt_q <= cnt_q + 1;
    end

    else if(inst_q[1]) begin
      query_q <= q_in;
    end

  end
end

endmodule

core/behavorial/mac_array/verilog/mac_col_tb.v
`timescale 1ns/1ps

module mac_col_tb;

reg clk = 0;
reg reset = 1;
reg [63:0] q_in = 0;
reg [1:0] i_inst = 0;

wire [21:0] out_0;
wire [63:0] q_out_0;
wire [1:0] o_inst_0;
wire fifo_wr_0;

wire [21:0] out_1;
wire [63:0] q_out_1;
wire [1:0] o_inst_1;
wire fifo_wr_1;

wire [21:0] out_2;
wire [63:0] q_out_2;
wire [1:0] o_inst_2;
wire fifo_wr_2;

parameter total_K = 3;
parameter total_Q = 3;

integer qk_file;
integer qk_scan_file;
integer  K[total_K-1:0][7:0];
integer  Q[total_Q-1:0][7:0];
integer  pred_result[total_K-1:0][total_Q-1:0];
//integer  result[total_cycle-1:0];
//integer  sum[total_cycle-1:0];

integer  captured_data;
`define NULL 0

integer i,j,k,t,p,q,s,u,m;


mac_col #(.bw(8), .bw_psum(22), .pr(8), .col_id(0)) mac_col_instance_0 (
      .clk(clk),
      .reset(reset),
      .out(out_0),
      .q_in(q_in),
      .q_out(q_out_0),
      .i_inst(i_inst),
      .o_inst(o_inst_0),
      .fifo_wr(fifo_wr_0)
);

mac_col #(.bw(8), .bw_psum(22), .pr(8), .col_id(1)) mac_col_instance_1 (
      .clk(clk),
      .reset(reset),
      .out(out_1),
      .q_in(q_out_0),
      .q_out(q_out_1),
      .i_inst(o_inst_0),
      .o_inst(o_inst_1),
      .fifo_wr(fifo_wr_1)
);

mac_col #(.bw(8), .bw_psum(22), .pr(8), .col_id(2)) mac_col_instance_2 (
      .clk(clk),
      .reset(reset),
      .out(out_2),
      .q_in(q_out_1),
      .q_out(q_out_2),
      .i_inst(o_inst_1),
      .o_inst(o_inst_2),
      .fifo_wr(fifo_wr_2)
);


initial begin 
      $dumpfile("mac_col_tb.vcd");
      $dumpvars(0, mac_col_tb);


      ///// Q data txt reading /////

      $display("##### Q data txt reading #####");


      qk_file = $fopen("qdata.txt", "r");

      for (q=0; q<total_Q; q=q+1) begin
            $display("Q vector: %d\n", q);
            for (j=0; j<8; j=j+1) begin
                  qk_scan_file = $fscanf(qk_file, "%d\n", captured_data);
                  Q[q][j] = captured_data;
                  $display("Data: %d\n", captured_data);
            end
      end
      /////////////////////////////////


      ///// K data txt reading /////

      $display("##### K data txt reading #####");


      qk_file = $fopen("kdata.txt", "r");

      for (q=0; q<total_K; q=q+1) begin
            $display("K vector: %d\n", q);
            for (j=0; j<8; j=j+1) begin
                  qk_scan_file = $fscanf(qk_file, "%d\n", captured_data);
                  K[q][j] = captured_data;
                  $display("Data: %d\n", captured_data);
            end
      end
      /////////////////////////////////


      ///// Predicted results calculation /////

      $display("##### K data txt reading #####");


      for (k=0; k<total_K; k=k+1) begin
            $display("K#: %d", k);
            for (q=0; q<total_Q; q=q+1) begin
                  $display("Q#: %d", q);
                  pred_result[k][q] = 0;
                  for (i=0; i<8; i=i+1) begin
                        pred_result[k][q] = pred_result[k][q] + Q[q][i]*K[k][i];
                  end
                  $display("Predicted psum: %d", pred_result[k][q]);
            end
      end
      /////////////////////////////////


      #1 clk = 1;
      #1 clk = 0; reset = 0;
      #1 clk = 1;
      #1 clk = 0; i_inst = 2'b01;
      #1 clk = 1;
      for (q=0; q<total_K; q=q+1) begin
            #1 clk = 0; q_in = {K[q][7][7:0], K[q][6][7:0], K[q][5][7:0], K[q][4][7:0], K[q][3][7:0], K[q][2][7:0], K[q][1][7:0], K[q][0][7:0]};
            if (q + 1 == total_K)
                  i_inst = 2'b00;
            #1 clk = 1;
      end

      for (i = 0; i < 10; i = i + 1) begin
            #1 clk = 0;
            #1 clk = 1;
      end

      #1 clk = 0; i_inst = 2'b10;
      #1 clk = 1;

      for (q=0; q<total_Q; q=q+1) begin
            #1 clk = 0; q_in = {Q[q][7][7:0], Q[q][6][7:0], Q[q][5][7:0], Q[q][4][7:0], Q[q][3][7:0], Q[q][2][7:0], Q[q][1][7:0], Q[q][0][7:0]};
            if (q + 1 == total_Q)
                  i_inst = 2'b00;
            #1 clk = 1;
      end

      for (i = 0; i < 10; i = i + 1) begin
            #1 clk = 0;
            #1 clk = 1;
      end

      #1 $display("Finished.");
      #1 $finish;
end

endmodule

dual_core/behavorial/mac_array/mac_col_tb.vcd
$date
	Sun Mar  9 20:16:47 2025
$end
$version
	Icarus Verilog
$end
$timescale
	1ps
$end
$scope module mac_col_tb $end
$var wire 64 ! q_out_2 [63:0] $end
$var wire 64 " q_out_1 [63:0] $end
$var wire 64 # q_out_0 [63:0] $end
$var wire 22 $ out_2 [21:0] $end
$var wire 22 % out_1 [21:0] $end
$var wire 22 & out_0 [21:0] $end
$var wire 2 ' o_inst_2 [1:0] $end
$var wire 2 ( o_inst_1 [1:0] $end
$var wire 2 ) o_inst_0 [1:0] $end
$var wire 1 * fifo_wr_2 $end
$var wire 1 + fifo_wr_1 $end
$var wire 1 , fifo_wr_0 $end
$var reg 1 - clk $end
$var reg 2 . i_inst [1:0] $end
$var reg 64 / q_in [63:0] $end
$var reg 1 0 reset $end
$var integer 32 1 captured_data [31:0] $end
$var integer 32 2 i [31:0] $end
$var integer 32 3 j [31:0] $end
$var integer 32 4 k [31:0] $end
$var integer 32 5 q [31:0] $end
$var integer 32 6 qk_file [31:0] $end
$var integer 32 7 qk_scan_file [31:0] $end
$scope module mac_col_instance_0 $end
$var wire 1 - clk $end
$var wire 2 8 i_inst [1:0] $end
$var wire 2 9 o_inst [1:0] $end
$var wire 22 : out [21:0] $end
$var wire 64 ; q_in [63:0] $end
$var wire 64 < q_out [63:0] $end
$var wire 1 0 reset $end
$var wire 22 = psum [21:0] $end
$var wire 1 , fifo_wr $end
$var reg 4 > cnt_q [3:0] $end
$var reg 2 ? inst_2q [1:0] $end
$var reg 2 @ inst_3q [1:0] $end
$var reg 2 A inst_4q [1:0] $end
$var reg 2 B inst_5q [1:0] $end
$var reg 2 C inst_6q [1:0] $end
$var reg 2 D inst_q [1:0] $end
$var reg 64 E key_q [63:0] $end
$var reg 1 F load_ready_q $end
$var reg 64 G query_q [63:0] $end
$scope module mac_8in_instance $end
$var wire 64 H a [63:0] $end
$var wire 64 I b [63:0] $end
$var wire 1 - clk $end
$var wire 1 0 reset $end
$var reg 22 J out [21:0] $end
$var reg 16 K product0 [15:0] $end
$var reg 16 L product1 [15:0] $end
$var reg 16 M product2 [15:0] $end
$var reg 16 N product3 [15:0] $end
$var reg 16 O product4 [15:0] $end
$var reg 16 P product5 [15:0] $end
$var reg 16 Q product6 [15:0] $end
$var reg 16 R product7 [15:0] $end
$var reg 22 S psum_0_0 [21:0] $end
$var reg 22 T psum_0_1 [21:0] $end
$var reg 22 U psum_0_2 [21:0] $end
$var reg 22 V psum_0_3 [21:0] $end
$var reg 22 W psum_1_0 [21:0] $end
$var reg 22 X psum_1_1 [21:0] $end
$upscope $end
$upscope $end
$scope module mac_col_instance_1 $end
$var wire 1 - clk $end
$var wire 2 Y i_inst [1:0] $end
$var wire 2 Z o_inst [1:0] $end
$var wire 22 [ out [21:0] $end
$var wire 64 \ q_in [63:0] $end
$var wire 64 ] q_out [63:0] $end
$var wire 1 0 reset $end
$var wire 22 ^ psum [21:0] $end
$var wire 1 + fifo_wr $end
$var reg 4 _ cnt_q [3:0] $end
$var reg 2 ` inst_2q [1:0] $end
$var reg 2 a inst_3q [1:0] $end
$var reg 2 b inst_4q [1:0] $end
$var reg 2 c inst_5q [1:0] $end
$var reg 2 d inst_6q [1:0] $end
$var reg 2 e inst_q [1:0] $end
$var reg 64 f key_q [63:0] $end
$var reg 1 g load_ready_q $end
$var reg 64 h query_q [63:0] $end
$scope module mac_8in_instance $end
$var wire 64 i a [63:0] $end
$var wire 64 j b [63:0] $end
$var wire 1 - clk $end
$var wire 1 0 reset $end
$var reg 22 k out [21:0] $end
$var reg 16 l product0 [15:0] $end
$var reg 16 m product1 [15:0] $end
$var reg 16 n product2 [15:0] $end
$var reg 16 o product3 [15:0] $end
$var reg 16 p product4 [15:0] $end
$var reg 16 q product5 [15:0] $end
$var reg 16 r product6 [15:0] $end
$var reg 16 s product7 [15:0] $end
$var reg 22 t psum_0_0 [21:0] $end
$var reg 22 u psum_0_1 [21:0] $end
$var reg 22 v psum_0_2 [21:0] $end
$var reg 22 w psum_0_3 [21:0] $end
$var reg 22 x psum_1_0 [21:0] $end
$var reg 22 y psum_1_1 [21:0] $end
$upscope $end
$upscope $end
$scope module mac_col_instance_2 $end
$var wire 1 - clk $end
$var wire 2 z i_inst [1:0] $end
$var wire 2 { o_inst [1:0] $end
$var wire 22 | out [21:0] $end
$var wire 64 } q_in [63:0] $end
$var wire 64 ~ q_out [63:0] $end
$var wire 1 0 reset $end
$var wire 22 !" psum [21:0] $end
$var wire 1 * fifo_wr $end
$var reg 4 "" cnt_q [3:0] $end
$var reg 2 #" inst_2q [1:0] $end
$var reg 2 $" inst_3q [1:0] $end
$var reg 2 %" inst_4q [1:0] $end
$var reg 2 &" inst_5q [1:0] $end
$var reg 2 '" inst_6q [1:0] $end
$var reg 2 (" inst_q [1:0] $end
$var reg 64 )" key_q [63:0] $end
$var reg 1 *" load_ready_q $end
$var reg 64 +" query_q [63:0] $end
$scope module mac_8in_instance $end
$var wire 64 ," a [63:0] $end
$var wire 64 -" b [63:0] $end
$var wire 1 - clk $end
$var wire 1 0 reset $end
$var reg 22 ." out [21:0] $end
$var reg 16 /" product0 [15:0] $end
$var reg 16 0" product1 [15:0] $end
$var reg 16 1" product2 [15:0] $end
$var reg 16 2" product3 [15:0] $end
$var reg 16 3" product4 [15:0] $end
$var reg 16 4" product5 [15:0] $end
$var reg 16 5" product6 [15:0] $end
$var reg 16 6" product7 [15:0] $end
$var reg 22 7" psum_0_0 [21:0] $end
$var reg 22 8" psum_0_1 [21:0] $end
$var reg 22 9" psum_0_2 [21:0] $end
$var reg 22 :" psum_0_3 [21:0] $end
$var reg 22 ;" psum_1_0 [21:0] $end
$var reg 22 <" psum_1_1 [21:0] $end
$upscope $end
$upscope $end
$upscope $end
$enddefinitions $end
#0
$dumpvars
bx <"
bx ;"
bx :"
bx 9"
bx 8"
bx 7"
bx 6"
bx 5"
bx 4"
bx 3"
bx 2"
bx 1"
bx 0"
bx /"
bx ."
bx -"
bx ,"
bx +"
x*"
bx )"
bx ("
bx '"
bx &"
bx %"
bx $"
bx #"
bx ""
bx !"
bx ~
bx }
bx |
bx {
bx z
bx y
bx x
bx w
bx v
bx u
bx t
bx s
bx r
bx q
bx p
bx o
bx n
bx m
bx l
bx k
bx j
bx i
bx h
xg
bx f
bx e
bx d
bx c
bx b
bx a
bx `
bx _
bx ^
bx ]
bx \
bx [
bx Z
bx Y
bx X
bx W
bx V
bx U
bx T
bx S
bx R
bx Q
bx P
bx O
bx N
bx M
bx L
bx K
bx J
bx I
bx H
bx G
xF
bx E
bx D
bx C
bx B
bx A
bx @
bx ?
bx >
bx =
bx <
b0 ;
bx :
bx 9
b0 8
b1 7
b10000000000000000000000000000100 6
b11 5
b11 4
b1000 3
b1000 2
b110 1
10
b0 /
b0 .
0-
x,
x+
x*
bx )
bx (
bx '
bx &
bx %
bx $
bx #
bx "
bx !
$end
#1000
0,
0+
0*
b0 R
b0 Q
b0 P
b0 O
b0 N
b0 M
b0 L
b0 K
b0 &
b0 :
b0 =
b0 J
b0 C
b0 B
b0 A
b0 @
b0 ?
b0 )
b0 9
b0 Y
b0 D
1F
b0 >
b0 s
b0 r
b0 q
b0 p
b0 o
b0 n
b0 m
b0 l
b0 %
b0 [
b0 ^
b0 k
b0 d
b0 c
b0 b
b0 a
b0 `
b0 (
b0 Z
b0 z
b0 e
1g
b0 _
b0 6"
b0 5"
b0 4"
b0 3"
b0 2"
b0 1"
b0 0"
b0 /"
b0 $
b0 |
b0 !"
b0 ."
b0 '"
b0 &"
b0 %"
b0 $"
b0 #"
b0 '
b0 {
b0 ("
1*"
b0 ""
1-
#2000
00
0-
#3000
bx $
bx |
bx !"
bx ."
b0 :"
b0 9"
b0 8"
b0 7"
bx 6"
bx 5"
bx 4"
bx 3"
bx 2"
bx 1"
bx 0"
bx /"
bx %
bx [
bx ^
bx k
b0 w
b0 v
b0 u
b0 t
bx s
bx r
bx q
bx p
bx o
bx n
bx m
bx l
bx &
bx :
bx =
bx J
b0 V
b0 U
b0 T
b0 S
bx R
bx Q
bx P
bx O
bx N
bx M
bx L
bx K
1-
#4000
b1 .
b1 8
0-
#5000
b0 X
b0 W
bx V
bx U
bx T
bx S
b1 )
b1 9
b1 Y
b1 D
b0 y
b0 x
bx w
bx v
bx u
bx t
b0 <"
b0 ;"
bx :"
bx 9"
bx 8"
bx 7"
b0 5
1-
#6000
b11100000000000000011111101111111111111111100000001111111010 /
b11100000000000000011111101111111111111111100000001111111010 ;
0-
#7000
b0 $
b0 |
b0 !"
b0 ."
bx <"
bx ;"
b1 (
b1 Z
b1 z
b1 e
b0 %
b0 [
b0 ^
b0 k
bx y
bx x
0F
b11100000000000000011111101111111111111111100000001111111010 E
b11100000000000000011111101111111111111111100000001111111010 I
b11100000000000000011111101111111111111111100000001111111010 #
b11100000000000000011111101111111111111111100000001111111010 <
b11100000000000000011111101111111111111111100000001111111010 \
b11100000000000000011111101111111111111111100000001111111010 G
b11100000000000000011111101111111111111111100000001111111010 H
b1 ?
b0 &
b0 :
b0 =
b0 J
bx X
bx W
b1 5
1-
#8000
b1111100111111011000000000000011000000000111110001111101100000000 /
b1111100111111011000000000000011000000000111110001111101100000000 ;
0-
#9000
bx &
bx :
bx =
bx J
b110001 R
b0 Q
b1 P
b11001 O
b1 N
b100 M
b1001 L
b100100 K
b1111100111111011000000000000011000000000111110001111101100000000 #
b1111100111111011000000000000011000000000111110001111101100000000 <
b1111100111111011000000000000011000000000111110001111101100000000 \
b1111100111111011000000000000011000000000111110001111101100000000 G
b1111100111111011000000000000011000000000111110001111101100000000 H
b1 @
bx %
bx [
bx ^
bx k
b1 _
b11100000000000000011111101111111111111111100000001111111010 "
b11100000000000000011111101111111111111111100000001111111010 ]
b11100000000000000011111101111111111111111100000001111111010 }
b11100000000000000011111101111111111111111100000001111111010 h
b11100000000000000011111101111111111111111100000001111111010 i
b1 `
bx $
bx |
bx !"
bx ."
b1 '
b1 {
b1 ("
b10 5
1-
#10000
b0 .
b0 8
b11000000110000001110000011100000011111110101111100100000100 /
b11000000110000001110000011100000011111110101111100100000100 ;
0-
#11000
b1 ""
b11100000000000000011111101111111111111111100000001111111010 !
b11100000000000000011111101111111111111111100000001111111010 ~
b11100000000000000011111101111111111111111100000001111111010 +"
b11100000000000000011111101111111111111111100000001111111010 ,"
b1 #"
0g
b1111100111111011000000000000011000000000111110001111101100000000 f
b1111100111111011000000000000011000000000111110001111101100000000 j
b1111100111111011000000000000011000000000111110001111101100000000 "
b1111100111111011000000000000011000000000111110001111101100000000 ]
b1111100111111011000000000000011000000000111110001111101100000000 }
b1111100111111011000000000000011000000000111110001111101100000000 h
b1111100111111011000000000000011000000000111110001111101100000000 i
b1 a
b11000000110000001110000011100000011111110101111100100000100 #
b11000000110000001110000011100000011111110101111100100000100 <
b11000000110000001110000011100000011111110101111100100000100 \
b11000000110000001110000011100000011111110101111100100000100 G
b11000000110000001110000011100000011111110101111100100000100 H
b1 A
b0 )
b0 9
b0 Y
b0 D
b110001 V
b11010 U
b101 T
b101101 S
b1111111111001111 R
b0 P
b1111111111100010 O
b0 N
b10000 M
b1111111111110001 L
b0 K
b0 2
b11 5
1-
#12000
0-
#13000
b1001011 X
b110010 W
b1111111111111111001111 V
b1111111111111111100010 U
b10000 T
b1111111111111111110001 S
b101010 R
b111 P
b1111111111011101 O
b1111111111111101 N
b1100 M
b1111111111101011 L
b1111111111101000 K
b1 B
b0 ?
b110001 s
b11001 r
b0 q
b100100 p
b0 o
b1000000 n
b11001 m
b0 l
b11000000110000001110000011100000011111110101111100100000100 "
b11000000110000001110000011100000011111110101111100100000100 ]
b11000000110000001110000011100000011111110101111100100000100 }
b11000000110000001110000011100000011111110101111100100000100 h
b11000000110000001110000011100000011111110101111100100000100 i
b1 b
b0 (
b0 Z
b0 z
b0 e
b10 ""
b1111100111111011000000000000011000000000111110001111101100000000 !
b1111100111111011000000000000011000000000111110001111101100000000 ~
b1111100111111011000000000000011000000000111110001111101100000000 +"
b1111100111111011000000000000011000000000111110001111101100000000 ,"
b1 $"
b1 2
1-
#14000
0-
#15000
0*"
b11000000110000001110000011100000011111110101111100100000100 )"
b11000000110000001110000011100000011111110101111100100000100 -"
b11000000110000001110000011100000011111110101111100100000100 !
b11000000110000001110000011100000011111110101111100100000100 ~
b11000000110000001110000011100000011111110101111100100000100 +"
b11000000110000001110000011100000011111110101111100100000100 ,"
b1 %"
b0 '
b0 {
b0 ("
b1 c
b0 `
b1001010 w
b100100 v
b1000000 u
b11001 t
b1111111111010110 s
b1111111111100010 r
b101010 p
b110000 n
b100011 m
b1 C
b0 @
b1111101 &
b1111101 :
b1111101 =
b1111101 J
b1111111111111110110001 X
b1 W
b101010 V
b1111111111111111100100 U
b1001 T
b1111111111111111010011 S
b10 2
1-
#16000
0-
#17000
b1111111111111110110010 &
b1111111111111110110010 :
b1111111111111110110010 =
b1111111111111110110010 J
b1110 X
b1111111111111111011100 W
b0 A
b1101110 y
b1011001 x
b1111111111111110111000 w
b101010 v
b110000 u
b100011 t
b1 d
b0 a
b100100 6"
b100100 5"
b110001 4"
b110001 3"
b1001 2"
b100100 1"
b110001 0"
b10000 /"
b1 &"
b0 #"
b11 2
1-
#18000
0-
#19000
b1 '"
b0 $"
b1001000 :"
b1100010 9"
b101101 8"
b1000001 7"
b0 b
b11000111 %
b11000111 [
b11000111 ^
b11000111 k
b1111111111111111100010 y
b1010011 x
b0 B
b1111111111111111101010 &
b1111111111111111101010 :
b1111111111111111101010 =
b1111111111111111101010 J
b100 2
1-
#20000
0-
#21000
b0 C
b110101 %
b110101 [
b110101 ^
b110101 k
b0 c
b10101010 <"
b1101110 ;"
b0 %"
b101 2
1-
#22000
0-
#23000
b0 &"
b100011000 $
b100011000 |
b100011000 !"
b100011000 ."
b0 d
b110 2
1-
#24000
0-
#25000
b0 '"
b111 2
1-
#26000
0-
#27000
b1000 2
1-
#28000
0-
#29000
b1001 2
1-
#30000
0-
#31000
b1010 2
1-
#32000
b10 .
b10 8
0-
#33000
b10 )
b10 9
b10 Y
b10 D
b0 5
1-
#34000
b1000000001000001101111111111111001111110110000011111111011 /
b1000000001000001101111111111111001111110110000011111111011 ;
0-
#35000
b10 (
b10 Z
b10 z
b10 e
b1000000001000001101111111111111001111110110000011111111011 #
b1000000001000001101111111111111001111110110000011111111011 <
b1000000001000001101111111111111001111110110000011111111011 \
b1000000001000001101111111111111001111110110000011111111011 G
b1000000001000001101111111111111001111110110000011111111011 H
b10 ?
b1 5
1-
#36000
b1111110100000001000001001111110111111011111111100000011111111100 /
b1111110100000001000001001111110111111011111111100000011111111100 ;
0-
#37000
b1110 R
b110 P
b101 O
b111 N
b1010 M
b10101 L
b11110 K
b1111110100000001000001001111110111111011111111100000011111111100 #
b1111110100000001000001001111110111111011111111100000011111111100 <
b1111110100000001000001001111110111111011111111100000011111111100 \
b1111110100000001000001001111110111111011111111100000011111111100 G
b1111110100000001000001001111110111111011111111100000011111111100 H
b10 @
b1000000001000001101111111111111001111110110000011111111011 "
b1000000001000001101111111111111001111110110000011111111011 ]
b1000000001000001101111111111111001111110110000011111111011 }
b1000000001000001101111111111111001111110110000011111111011 h
b1000000001000001101111111111111001111110110000011111111011 i
b10 `
b10 '
b10 {
b10 ("
b10 5
1-
#38000
b0 .
b0 8
b10000001010000000011111100111111001111111111111100 /
b10000001010000000011111100111111001111111111111100 ;
0-
#39000
b1000000001000001101111111111111001111110110000011111111011 !
b1000000001000001101111111111111001111110110000011111111011 ~
b1000000001000001101111111111111001111110110000011111111011 +"
b1000000001000001101111111111111001111110110000011111111011 ,"
b10 #"
b1111110100000001000001001111110111111011111111100000011111111100 "
b1111110100000001000001001111110111111011111111100000011111111100 ]
b1111110100000001000001001111110111111011111111100000011111111100 }
b1111110100000001000001001111110111111011111111100000011111111100 h
b1111110100000001000001001111110111111011111111100000011111111100 i
b10 a
b1111111111110010 s
b1111111111111011 r
b1111111111111010 p
b101000 n
b1111111111011101 m
b10000001010000000011111100111111001111111111111100 #
b10000001010000000011111100111111001111111111111100 <
b10000001010000000011111100111111001111111111111100 \
b10000001010000000011111100111111001111111111111100 G
b10000001010000000011111100111111001111111111111100 H
b10 A
b0 )
b0 9
b0 Y
b0 D
b1110 V
b1011 U
b10001 T
b110011 S
b1111111111101011 R
b100 P
b1111 O
b101 N
b100 M
b11000 K
b0 2
b11 5
1-
#40000
0-
#41000
b11001 X
b1000100 W
b1111111111111111101011 V
b10011 U
b1001 T
b101101 S
b0 R
b101 P
b0 O
b100 N
b1000 M
b1111111111111101 L
b10 B
b0 ?
b1111111111111111101101 w
b1111111111111111111010 v
b101000 u
b1111111111111111011101 t
b10101 s
b1111111111101110 p
b10000 n
b10000001010000000011111100111111001111111111111100 "
b10000001010000000011111100111111001111111111111100 ]
b10000001010000000011111100111111001111111111111100 }
b10000001010000000011111100111111001111111111111100 h
b10000001010000000011111100111111001111111111111100 i
b10 b
b0 (
b0 Z
b0 z
b0 e
b1100 6"
b110 5"
b101010 4"
b1111111111111001 3"
b1111111111101011 2"
b11110 1"
b1111111111001111 0"
b1111111111101100 /"
b1111110100000001000001001111110111111011111111100000011111111100 !
b1111110100000001000001001111110111111011111111100000011111111100 ~
b1111110100000001000001001111110111111011111111100000011111111100 +"
b1111110100000001000001001111110111111011111111100000011111111100 ,"
b10 $"
b1 2
1-
#42000
0-
#43000
1,
b10000001010000000011111100111111001111111111111100 !
b10000001010000000011111100111111001111111111111100 ~
b10000001010000000011111100111111001111111111111100 +"
b10000001010000000011111100111111001111111111111100 ,"
b10 %"
b0 '
b0 {
b0 ("
b10010 :"
b100011 9"
b1001 8"
b1111111111111110111011 7"
b1111111111101110 6"
b11100 4"
b1111111111101011 3"
b1111111111110001 2"
b1100 1"
b1111111111110000 /"
b10 c
b0 `
b1111111111111111100111 y
b101 x
b10000 w
b1111111111111111101110 v
b10000 u
b0 s
b1111111111110110 r
b0 p
b100000 n
b101 m
b10 C
b0 @
b1011101 &
b1011101 :
b1011101 =
b1011101 J
b1111111111111111111110 X
b110110 W
b0 V
b101 U
b1100 T
b10101 S
b10 2
1-
#44000
0-
#45000
1+
b110100 &
b110100 :
b110100 =
b110100 J
b101 X
b100001 W
b0 A
b1111111111111111101100 %
b1111111111111111101100 [
b1111111111111111101100 ^
b1111111111111111101100 k
b1111111111111111111110 y
b1111111111111111101101 x
b1111111111111111110110 w
b0 v
b100000 u
b101 t
b10 d
b0 a
b110101 <"
b1111111111111111000100 ;"
b1111111111111111110100 :"
b111 9"
b1111111111111111111101 8"
b1111111111111110111111 7"
b0 6"
b1100 5"
b100011 4"
b0 3"
b1111111111110100 2"
b11000 1"
b111 0"
b10 &"
b0 #"
b11 2
1-
#46000
0-
#47000
1*
b10 '"
b0 $"
b1111111111111111111001 $
b1111111111111111111001 |
b1111111111111111111001 !"
b1111111111111111111001 ."
b1111111111111111111011 <"
b1111111111111110111100 ;"
b1100 :"
b100011 9"
b1100 8"
b1111111111111111110111 7"
b0 b
b1111111111111111101011 %
b1111111111111111101011 [
b1111111111111111101011 ^
b1111111111111111101011 k
b1111111111111111110110 y
b100101 x
b0 B
b100110 &
b100110 :
b100110 =
b100110 J
b100 2
1-
#48000
0-
#49000
0,
b0 C
b11011 %
b11011 [
b11011 ^
b11011 k
b0 c
b1111111111111110110111 $
b1111111111111110110111 |
b1111111111111110110111 !"
b1111111111111110110111 ."
b101111 <"
b11 ;"
b0 %"
b101 2
1-
#50000
0-
#51000
0+
b0 &"
b110010 $
b110010 |
b110010 !"
b110010 ."
b0 d
b110 2
1-
#52000
0-
#53000
0*
b0 '"
b111 2
1-
#54000
0-
#55000
b1000 2
1-
#56000
0-
#57000
b1001 2
1-
#58000
0-
#59000
b1010 2
1-
