core/behavorial/mac_col/verilog/mac_8in.v
module mac_8in (out, a, b, clk, reset);

parameter bw = 8;
parameter bw_psum = 2*bw+6;
parameter pr = 8;

output reg signed [bw_psum-1:0] out;
input  [pr*bw-1:0] a;
input  [pr*bw-1:0] b;


reg		[2*bw-1:0]	product0	;
reg		[2*bw-1:0]	product1	;
reg		[2*bw-1:0]	product2	;
reg		[2*bw-1:0]	product3	;
reg		[2*bw-1:0]	product4	;
reg		[2*bw-1:0]	product5	;
reg		[2*bw-1:0]	product6	;
reg		[2*bw-1:0]	product7	;

always @ (posedge clk) begin
	if (reset) begin
		out <= 0;
		product0 <= 0;
		product1 <= 0;
		product2 <= 0;
		product3 <= 0;
		product4 <= 0;
		product5 <= 0;
		product6 <= 0;
		product7 <= 0;
	end
	else begin
		product0	<=	{{(bw){a[bw*	1	-1]}},	a[bw*	1	-1:bw*	0	]}	*	{{(bw){b[bw*	1	-1]}},	b[bw*	1	-1:	bw*	0	]};
		product1	<=	{{(bw){a[bw*	2	-1]}},	a[bw*	2	-1:bw*	1	]}	*	{{(bw){b[bw*	2	-1]}},	b[bw*	2	-1:	bw*	1	]};
		product2	<=	{{(bw){a[bw*	3	-1]}},	a[bw*	3	-1:bw*	2	]}	*	{{(bw){b[bw*	3	-1]}},	b[bw*	3	-1:	bw*	2	]};
		product3	<=	{{(bw){a[bw*	4	-1]}},	a[bw*	4	-1:bw*	3	]}	*	{{(bw){b[bw*	4	-1]}},	b[bw*	4	-1:	bw*	3	]};
		product4	<=	{{(bw){a[bw*	5	-1]}},	a[bw*	5	-1:bw*	4	]}	*	{{(bw){b[bw*	5	-1]}},	b[bw*	5	-1:	bw*	4	]};
		product5	<=	{{(bw){a[bw*	6	-1]}},	a[bw*	6	-1:bw*	5	]}	*	{{(bw){b[bw*	6	-1]}},	b[bw*	6	-1:	bw*	5	]};
		product6	<=	{{(bw){a[bw*	7	-1]}},	a[bw*	7	-1:bw*	6	]}	*	{{(bw){b[bw*	7	-1]}},	b[bw*	7	-1:	bw*	6	]};
		product7	<=	{{(bw){a[bw*	8	-1]}},	a[bw*	8	-1:bw*	7	]}	*	{{(bw){b[bw*	8	-1]}},	b[bw*	8	-1:	bw*	7	]};

		out <= 
				{{(4){product0[2*bw-1]}},product0	}
			+	{{(4){product1[2*bw-1]}},product1	}
			+	{{(4){product2[2*bw-1]}},product2	}
			+	{{(4){product3[2*bw-1]}},product3	}
			+	{{(4){product4[2*bw-1]}},product4	}
			+	{{(4){product5[2*bw-1]}},product5	}
			+	{{(4){product6[2*bw-1]}},product6	}
			+	{{(4){product7[2*bw-1]}},product7	};
	end
end








endmodule

core/behavorial/mac_col/verilog/mac_col.v
module mac_col (clk, reset, out, q_in, q_out, i_inst, fifo_wr, o_inst);

parameter bw = 8;
parameter bw_psum = 2*bw+6;
parameter pr = 8;
parameter col_id = 0;

output signed [bw_psum-1:0] out;
input  signed [pr*bw-1:0] q_in;
output signed [pr*bw-1:0] q_out;
input  clk, reset;
input  [1:0] i_inst; // [1]: execute, [0]: load 
output [1:0] o_inst; // [1]: execute, [0]: load 
output fifo_wr;
reg    load_ready_q;
reg    [3:0] cnt_q;
reg    [1:0] inst_q;
reg    [1:0] inst_2q;
reg   signed [pr*bw-1:0] query_q;
reg   signed [pr*bw-1:0] key_q;
wire  signed [bw_psum-1:0] psum;

assign o_inst = inst_q;
assign fifo_wr = inst_2q[1];
assign q_out  = query_q;
assign out = psum;

mac_8in #(.bw(8), .bw_psum(19), .pr(8)) mac_8in_instance (
  .a(query_q), 
  .b(key_q),
  .out(psum),
  .clk(clk),
  .reset(reset)
); 


always @ (posedge clk) begin

  if (reset) begin

    cnt_q <= 0;
    load_ready_q <= 1;
    inst_q <= 0;
    inst_2q <= 0;

  end

  else begin

    inst_q <= i_inst;
    inst_2q <= inst_q;

    if (inst_q[0]) begin //load

       query_q <= q_in;

       if (cnt_q == col_id && load_ready_q) begin
         key_q <= q_in;
         load_ready_q <= 0;
       end

       else if (load_ready_q)
         cnt_q <= cnt_q + 1;
    end

    else if(inst_q[1]) begin
      query_q <= q_in;
    end

  end
end

endmodule

core/behavorial/mac_col/verilog/mac_col_tb.v
`timescale 1ns/1ps

module mac_col_tb;

reg clk = 0;
reg reset = 1;
reg [63:0] q_in = 0;
reg [1:0] i_inst = 0;

integer i = 0;

wire [31:0] out_0;
wire [63:0] q_out_0;
wire [1:0] o_inst_0;
wire fifo_wr_0;

wire [31:0] out_1;
wire [63:0] q_out_1;
wire [1:0] o_inst_1;
wire fifo_wr_1;

wire [31:0] out_2;
wire [63:0] q_out_2;
wire [1:0] o_inst_2;
wire fifo_wr_2;


mac_col #(.bw(8), .bw_psum(32), .pr(8), .col_id(0)) mac_col_instance_0 (
      .clk(clk),
      .reset(reset),
      .out(out_0),
      .q_in(q_in),
      .q_out(q_out_0),
      .i_inst(i_inst),
      .o_inst(o_inst_0),
      .fifo_wr(fifo_wr_0)
);

mac_col #(.bw(8), .bw_psum(32), .pr(8), .col_id(1)) mac_col_instance_1 (
      .clk(clk),
      .reset(reset),
      .out(out_1),
      .q_in(q_out_0),
      .q_out(q_out_1),
      .i_inst(o_inst_0),
      .o_inst(o_inst_1),
      .fifo_wr(fifo_wr_1)
);

mac_col #(.bw(8), .bw_psum(32), .pr(8), .col_id(2)) mac_col_instance_2 (
      .clk(clk),
      .reset(reset),
      .out(out_2),
      .q_in(q_out_1),
      .q_out(q_out_2),
      .i_inst(o_inst_1),
      .o_inst(o_inst_2),
      .fifo_wr(fifo_wr_2)
);


initial begin 
      $dumpfile("mac_col_tb.vcd");
      $dumpvars(0, mac_col_tb);
      #1 clk = 1;
      #1 clk = 0; reset = 0;
      #1 clk = 1;
      #1 clk = 0; i_inst = 2'b01;
      #1 clk = 1;
      #1 clk = 0; q_in = {8'd1, 8'd2, 8'd3, 8'd4, 8'd5, 8'd6, 8'd7, 8'd8};
      #1 clk = 1;
      #1 clk = 0; q_in = {8'd1, 8'd3, 8'd5, 8'd7, 8'd9, 8'd11, 8'd13, 8'd15};
      #1 clk = 1;
      #1 clk = 0; q_in = {8'd2, 8'd4, 8'd6, 8'd8, 8'd10, 8'd12, 8'd14, 8'd16}; i_inst = 2'b00;

      for (i = 0; i < 10; i = i + 1) begin
            #1 clk = 1;
            #1 clk = 0;
            #1 clk = 1;
            #1 clk = 0;
      end

      #1 clk = 1;
      #1 clk = 0; i_inst = 2'b10;
      #1 clk = 1;
      #1 clk = 0; q_in = {8'd1, 8'd2, 8'd3, 8'd4, 8'd5, 8'd6, 8'd7, 8'd8};
      #1 clk = 1;
      #1 clk = 0; q_in = {8'd1, 8'd3, 8'd5, 8'd7, 8'd9, 8'd11, 8'd13, 8'd15};
      #1 clk = 1;
      #1 clk = 0; q_in = {8'd2, 8'd4, 8'd6, 8'd8, 8'd10, 8'd12, 8'd14, 8'd16}; i_inst = 2'b00;

      for (i = 0; i < 10; i = i + 1) begin
            #1 clk = 1;
            #1 clk = 0;
            #1 clk = 1;
            #1 clk = 0;
      end

      #1 $display("Finished.");
      #1 $finish;
end

endmodule

core/behavorial/mac_col/mac_col_tb.vcd
$date
	Tue Mar  4 21:57:57 2025
$end
$version
	Icarus Verilog
$end
$timescale
	1ps
$end
$scope module mac_col_tb $end
$var wire 64 ! q_out_2 [63:0] $end
$var wire 64 " q_out_1 [63:0] $end
$var wire 64 # q_out_0 [63:0] $end
$var wire 32 $ out_2 [31:0] $end
$var wire 32 % out_1 [31:0] $end
$var wire 32 & out_0 [31:0] $end
$var wire 2 ' o_inst_2 [1:0] $end
$var wire 2 ( o_inst_1 [1:0] $end
$var wire 2 ) o_inst_0 [1:0] $end
$var wire 1 * fifo_wr_2 $end
$var wire 1 + fifo_wr_1 $end
$var wire 1 , fifo_wr_0 $end
$var reg 1 - clk $end
$var reg 2 . i_inst [1:0] $end
$var reg 64 / q_in [63:0] $end
$var reg 1 0 reset $end
$var integer 32 1 i [31:0] $end
$scope module mac_col_instance_0 $end
$var wire 1 - clk $end
$var wire 2 2 i_inst [1:0] $end
$var wire 2 3 o_inst [1:0] $end
$var wire 32 4 out [31:0] $end
$var wire 64 5 q_in [63:0] $end
$var wire 64 6 q_out [63:0] $end
$var wire 1 0 reset $end
$var wire 32 7 psum [31:0] $end
$var wire 1 , fifo_wr $end
$var reg 4 8 cnt_q [3:0] $end
$var reg 2 9 inst_2q [1:0] $end
$var reg 2 : inst_q [1:0] $end
$var reg 64 ; key_q [63:0] $end
$var reg 1 < load_ready_q $end
$var reg 64 = query_q [63:0] $end
$scope module mac_8in_instance $end
$var wire 64 > a [63:0] $end
$var wire 64 ? b [63:0] $end
$var wire 16 @ product7 [15:0] $end
$var wire 16 A product6 [15:0] $end
$var wire 16 B product5 [15:0] $end
$var wire 16 C product4 [15:0] $end
$var wire 16 D product3 [15:0] $end
$var wire 16 E product2 [15:0] $end
$var wire 16 F product1 [15:0] $end
$var wire 16 G product0 [15:0] $end
$var wire 19 H out [18:0] $end
$upscope $end
$upscope $end
$scope module mac_col_instance_1 $end
$var wire 1 - clk $end
$var wire 2 I i_inst [1:0] $end
$var wire 2 J o_inst [1:0] $end
$var wire 32 K out [31:0] $end
$var wire 64 L q_in [63:0] $end
$var wire 64 M q_out [63:0] $end
$var wire 1 0 reset $end
$var wire 32 N psum [31:0] $end
$var wire 1 + fifo_wr $end
$var reg 4 O cnt_q [3:0] $end
$var reg 2 P inst_2q [1:0] $end
$var reg 2 Q inst_q [1:0] $end
$var reg 64 R key_q [63:0] $end
$var reg 1 S load_ready_q $end
$var reg 64 T query_q [63:0] $end
$scope module mac_8in_instance $end
$var wire 64 U a [63:0] $end
$var wire 64 V b [63:0] $end
$var wire 16 W product7 [15:0] $end
$var wire 16 X product6 [15:0] $end
$var wire 16 Y product5 [15:0] $end
$var wire 16 Z product4 [15:0] $end
$var wire 16 [ product3 [15:0] $end
$var wire 16 \ product2 [15:0] $end
$var wire 16 ] product1 [15:0] $end
$var wire 16 ^ product0 [15:0] $end
$var wire 19 _ out [18:0] $end
$upscope $end
$upscope $end
$scope module mac_col_instance_2 $end
$var wire 1 - clk $end
$var wire 2 ` i_inst [1:0] $end
$var wire 2 a o_inst [1:0] $end
$var wire 32 b out [31:0] $end
$var wire 64 c q_in [63:0] $end
$var wire 64 d q_out [63:0] $end
$var wire 1 0 reset $end
$var wire 32 e psum [31:0] $end
$var wire 1 * fifo_wr $end
$var reg 4 f cnt_q [3:0] $end
$var reg 2 g inst_2q [1:0] $end
$var reg 2 h inst_q [1:0] $end
$var reg 64 i key_q [63:0] $end
$var reg 1 j load_ready_q $end
$var reg 64 k query_q [63:0] $end
$scope module mac_8in_instance $end
$var wire 64 l a [63:0] $end
$var wire 64 m b [63:0] $end
$var wire 16 n product7 [15:0] $end
$var wire 16 o product6 [15:0] $end
$var wire 16 p product5 [15:0] $end
$var wire 16 q product4 [15:0] $end
$var wire 16 r product3 [15:0] $end
$var wire 16 s product2 [15:0] $end
$var wire 16 t product1 [15:0] $end
$var wire 16 u product0 [15:0] $end
$var wire 19 v out [18:0] $end
$upscope $end
$upscope $end
$upscope $end
$enddefinitions $end
#0
$dumpvars
bx v
bx u
bx t
bx s
bx r
bx q
bx p
bx o
bx n
bx m
bx l
bx k
xj
bx i
bx h
bx g
bx f
b0xxxxxxxxxxxxxxxxxxx e
bx d
bx c
b0xxxxxxxxxxxxxxxxxxx b
bx a
bx `
bx _
bx ^
bx ]
bx \
bx [
bx Z
bx Y
bx X
bx W
bx V
bx U
bx T
xS
bx R
bx Q
bx P
bx O
b0xxxxxxxxxxxxxxxxxxx N
bx M
bx L
b0xxxxxxxxxxxxxxxxxxx K
bx J
bx I
bx H
bx G
bx F
bx E
bx D
bx C
bx B
bx A
bx @
bx ?
bx >
bx =
x<
bx ;
bx :
bx 9
bx 8
b0xxxxxxxxxxxxxxxxxxx 7
bx 6
b0 5
b0xxxxxxxxxxxxxxxxxxx 4
bx 3
b0 2
b0 1
10
b0 /
b0 .
0-
x,
x+
x*
bx )
bx (
bx '
b0xxxxxxxxxxxxxxxxxxx &
b0xxxxxxxxxxxxxxxxxxx %
b0xxxxxxxxxxxxxxxxxxx $
bx #
bx "
bx !
$end
#1000
0,
0+
0*
b0 9
b0 )
b0 3
b0 I
b0 :
1<
b0 8
b0 P
b0 (
b0 J
b0 `
b0 Q
1S
b0 O
b0 g
b0 '
b0 a
b0 h
1j
b0 f
1-
#2000
00
0-
#3000
1-
#4000
b1 .
b1 2
0-
#5000
b1 )
b1 3
b1 I
b1 :
1-
#6000
b100000010000000110000010000000101000001100000011100001000 /
b100000010000000110000010000000101000001100000011100001000 5
0-
#7000
b11001100 &
b11001100 4
b11001100 7
b11001100 H
b1000000 G
b110001 F
b100100 E
b11001 D
b10000 C
b1001 B
b100 A
b1 @
b1 (
b1 J
b1 `
b1 Q
0<
b100000010000000110000010000000101000001100000011100001000 ;
b100000010000000110000010000000101000001100000011100001000 ?
b100000010000000110000010000000101000001100000011100001000 #
b100000010000000110000010000000101000001100000011100001000 6
b100000010000000110000010000000101000001100000011100001000 L
b100000010000000110000010000000101000001100000011100001000 =
b100000010000000110000010000000101000001100000011100001000 >
b1 9
1-
#8000
b100000011000001010000011100001001000010110000110100001111 /
b100000011000001010000011100001001000010110000110100001111 5
0-
#9000
b101110100 &
b101110100 4
b101110100 7
b101110100 H
b1111000 G
b1011011 F
b1000010 E
b101101 D
b11100 C
b1111 B
b110 A
b100000011000001010000011100001001000010110000110100001111 #
b100000011000001010000011100001001000010110000110100001111 6
b100000011000001010000011100001001000010110000110100001111 L
b100000011000001010000011100001001000010110000110100001111 =
b100000011000001010000011100001001000010110000110100001111 >
b1 O
b100000010000000110000010000000101000001100000011100001000 "
b100000010000000110000010000000101000001100000011100001000 M
b100000010000000110000010000000101000001100000011100001000 c
b100000010000000110000010000000101000001100000011100001000 T
b100000010000000110000010000000101000001100000011100001000 U
b1 P
b1 '
b1 a
b1 h
1-
#10000
b0 .
b0 2
b1000000100000001100000100000001010000011000000111000010000 /
b1000000100000001100000100000001010000011000000111000010000 5
0-
#11000
b1010101000 %
b1010101000 K
b1010101000 N
b1010101000 _
b110011000 &
b110011000 4
b110011000 7
b110011000 H
b11100001 ^
b10101001 ]
b1111001 \
b1010001 [
b110001 Z
b11001 Y
b1001 X
b1 W
b10000000 G
b1100010 F
b1001000 E
b110010 D
b100000 C
b10010 B
b1000 A
b10 @
b1 f
b100000010000000110000010000000101000001100000011100001000 !
b100000010000000110000010000000101000001100000011100001000 d
b100000010000000110000010000000101000001100000011100001000 k
b100000010000000110000010000000101000001100000011100001000 l
b1 g
0S
b100000011000001010000011100001001000010110000110100001111 R
b100000011000001010000011100001001000010110000110100001111 V
b100000011000001010000011100001001000010110000110100001111 "
b100000011000001010000011100001001000010110000110100001111 M
b100000011000001010000011100001001000010110000110100001111 c
b100000011000001010000011100001001000010110000110100001111 T
b100000011000001010000011100001001000010110000110100001111 U
b1000000100000001100000100000001010000011000000111000010000 #
b1000000100000001100000100000001010000011000000111000010000 6
b1000000100000001100000100000001010000011000000111000010000 L
b1000000100000001100000100000001010000011000000111000010000 =
b1000000100000001100000100000001010000011000000111000010000 >
b0 )
b0 3
b0 I
b0 :
1-
#12000
0-
#13000
b1011101000 %
b1011101000 K
b1011101000 N
b1011101000 _
b11110000 ^
b10110110 ]
b10000100 \
b1011010 [
b111000 Z
b11110 Y
b1100 X
b10 W
b0 9
b1000000100000001100000100000001010000011000000111000010000 "
b1000000100000001100000100000001010000011000000111000010000 M
b1000000100000001100000100000001010000011000000111000010000 c
b1000000100000001100000100000001010000011000000111000010000 T
b1000000100000001100000100000001010000011000000111000010000 U
b0 (
b0 J
b0 `
b0 Q
b10 f
b100000011000001010000011100001001000010110000110100001111 !
b100000011000001010000011100001001000010110000110100001111 d
b100000011000001010000011100001001000010110000110100001111 k
b100000011000001010000011100001001000010110000110100001111 l
1-
#14000
b1 1
0-
#15000
b1100110000 $
b1100110000 b
b1100110000 e
b1100110000 v
b100000000 u
b11000100 t
b10010000 s
b1100100 r
b1000000 q
b100100 p
b10000 o
b100 n
0j
b1000000100000001100000100000001010000011000000111000010000 i
b1000000100000001100000100000001010000011000000111000010000 m
b1000000100000001100000100000001010000011000000111000010000 !
b1000000100000001100000100000001010000011000000111000010000 d
b1000000100000001100000100000001010000011000000111000010000 k
b1000000100000001100000100000001010000011000000111000010000 l
b0 '
b0 a
b0 h
b0 P
1-
#16000
0-
#17000
b0 g
1-
#18000
b10 1
0-
#19000
1-
#20000
0-
#21000
1-
#22000
b11 1
0-
#23000
1-
#24000
0-
#25000
1-
#26000
b100 1
0-
#27000
1-
#28000
0-
#29000
1-
#30000
b101 1
0-
#31000
1-
#32000
0-
#33000
1-
#34000
b110 1
0-
#35000
1-
#36000
0-
#37000
1-
#38000
b111 1
0-
#39000
1-
#40000
0-
#41000
1-
#42000
b1000 1
0-
#43000
1-
#44000
0-
#45000
1-
#46000
b1001 1
0-
#47000
1-
#48000
0-
#49000
1-
#50000
b1010 1
0-
#51000
1-
#52000
b10 .
b10 2
0-
#53000
b10 )
b10 3
b10 I
b10 :
1-
#54000
b100000010000000110000010000000101000001100000011100001000 /
b100000010000000110000010000000101000001100000011100001000 5
0-
#55000
b11001100 &
b11001100 4
b11001100 7
b11001100 H
b1000000 G
b110001 F
b100100 E
b11001 D
b10000 C
b1001 B
b100 A
b1 @
1,
b10 (
b10 J
b10 `
b10 Q
b100000010000000110000010000000101000001100000011100001000 #
b100000010000000110000010000000101000001100000011100001000 6
b100000010000000110000010000000101000001100000011100001000 L
b100000010000000110000010000000101000001100000011100001000 =
b100000010000000110000010000000101000001100000011100001000 >
b10 9
1-
#56000
b100000011000001010000011100001001000010110000110100001111 /
b100000011000001010000011100001001000010110000110100001111 5
0-
#57000
b101110100 &
b101110100 4
b101110100 7
b101110100 H
b101110100 %
b101110100 K
b101110100 N
b101110100 _
b1111000 G
b1011011 F
b1000010 E
b101101 D
b11100 C
b1111 B
b110 A
b1111000 ^
b1011011 ]
b1000010 \
b101101 [
b11100 Z
b1111 Y
b110 X
b1 W
1+
b100000011000001010000011100001001000010110000110100001111 #
b100000011000001010000011100001001000010110000110100001111 6
b100000011000001010000011100001001000010110000110100001111 L
b100000011000001010000011100001001000010110000110100001111 =
b100000011000001010000011100001001000010110000110100001111 >
b100000010000000110000010000000101000001100000011100001000 "
b100000010000000110000010000000101000001100000011100001000 M
b100000010000000110000010000000101000001100000011100001000 c
b100000010000000110000010000000101000001100000011100001000 T
b100000010000000110000010000000101000001100000011100001000 U
b10 P
b10 '
b10 a
b10 h
1-
#58000
b0 1
b0 .
b0 2
b1000000100000001100000100000001010000011000000111000010000 /
b1000000100000001100000100000001010000011000000111000010000 5
0-
#59000
b110011000 $
b110011000 b
b110011000 e
b110011000 v
b1010101000 %
b1010101000 K
b1010101000 N
b1010101000 _
b110011000 &
b110011000 4
b110011000 7
b110011000 H
b10000000 u
b1100010 t
b1001000 s
b110010 r
b100000 q
b10010 p
b1000 o
b10 n
1*
b11100001 ^
b10101001 ]
b1111001 \
b1010001 [
b110001 Z
b11001 Y
b1001 X
b10000000 G
b1100010 F
b1001000 E
b110010 D
b100000 C
b10010 B
b1000 A
b10 @
b100000010000000110000010000000101000001100000011100001000 !
b100000010000000110000010000000101000001100000011100001000 d
b100000010000000110000010000000101000001100000011100001000 k
b100000010000000110000010000000101000001100000011100001000 l
b10 g
b100000011000001010000011100001001000010110000110100001111 "
b100000011000001010000011100001001000010110000110100001111 M
b100000011000001010000011100001001000010110000110100001111 c
b100000011000001010000011100001001000010110000110100001111 T
b100000011000001010000011100001001000010110000110100001111 U
b1000000100000001100000100000001010000011000000111000010000 #
b1000000100000001100000100000001010000011000000111000010000 6
b1000000100000001100000100000001010000011000000111000010000 L
b1000000100000001100000100000001010000011000000111000010000 =
b1000000100000001100000100000001010000011000000111000010000 >
b0 )
b0 3
b0 I
b0 :
1-
#60000
0-
#61000
b1011101000 %
b1011101000 K
b1011101000 N
b1011101000 _
b1011101000 $
b1011101000 b
b1011101000 e
b1011101000 v
0,
b11110000 ^
b10110110 ]
b10000100 \
b1011010 [
b111000 Z
b11110 Y
b1100 X
b10 W
b11110000 u
b10110110 t
b10000100 s
b1011010 r
b111000 q
b11110 p
b1100 o
b0 9
b1000000100000001100000100000001010000011000000111000010000 "
b1000000100000001100000100000001010000011000000111000010000 M
b1000000100000001100000100000001010000011000000111000010000 c
b1000000100000001100000100000001010000011000000111000010000 T
b1000000100000001100000100000001010000011000000111000010000 U
b0 (
b0 J
b0 `
b0 Q
b100000011000001010000011100001001000010110000110100001111 !
b100000011000001010000011100001001000010110000110100001111 d
b100000011000001010000011100001001000010110000110100001111 k
b100000011000001010000011100001001000010110000110100001111 l
1-
#62000
b1 1
0-
#63000
b1100110000 $
b1100110000 b
b1100110000 e
b1100110000 v
b100000000 u
b11000100 t
b10010000 s
b1100100 r
b1000000 q
b100100 p
b10000 o
b100 n
0+
b1000000100000001100000100000001010000011000000111000010000 !
b1000000100000001100000100000001010000011000000111000010000 d
b1000000100000001100000100000001010000011000000111000010000 k
b1000000100000001100000100000001010000011000000111000010000 l
b0 '
b0 a
b0 h
b0 P
1-
#64000
0-
#65000
0*
b0 g
1-
#66000
b10 1
0-
#67000
1-
#68000
0-
#69000
1-
#70000
b11 1
0-
#71000
1-
#72000
0-
#73000
1-
#74000
b100 1
0-
#75000
1-
#76000
0-
#77000
1-
#78000
b101 1
0-
#79000
1-
#80000
0-
#81000
1-
#82000
b110 1
0-
#83000
1-
#84000
0-
#85000
1-
#86000
b111 1
0-
#87000
1-
#88000
0-
#89000
1-
#90000
b1000 1
0-
#91000
1-
#92000
0-
#93000
1-
#94000
b1001 1
0-
#95000
1-
#96000
0-
#97000
1-
#98000
b1010 1
0-
